{
  "schema": 1,
  "source": "chapter_computer-vision/fcn.md",
  "framework": "tensorflow",
  "provenance": {
    "framework_version": "tensorflow==2.21.0",
    "d2l_lib_fingerprint": "sha256:c72d083560a24a71af2bd3a75163ae77dedcf6621c390c51b11cb22078db5ce6",
    "max_inline_bytes": 0
  },
  "cells": {
    "fcn-fully-convolutional-networks": {
      "code_fingerprint": "sha256:995e4fb28000f606aa91dc434b59061c5d0e07e40dc5314344cbfd4eeabbe76d",
      "kind": "text",
      "outputs": []
    },
    "fcn-the-model-1": {
      "code_fingerprint": "sha256:53791360969cf130ad5c0a2a9d185fdfeac6998aca268b1e6c1772c3d126a8b6",
      "kind": "text",
      "outputs": [
        {
          "type": "execute_result",
          "text": "[<ReLU name=re_lu_16, built=True>,\n <GlobalAveragePooling2D name=global_average_pooling2d, built=True>,\n <Dense name=dense, built=True>]"
        }
      ]
    },
    "fcn-the-model-2": {
      "code_fingerprint": "sha256:53b0ba069ce9ef8f98db31ffc525e45754c50a1e7e79d9f8d6f018e7c8179624",
      "kind": "text",
      "outputs": []
    },
    "fcn-the-model-3": {
      "code_fingerprint": "sha256:916ea499eb9aeddc1275ccc60254975d693bc29e4e1d8be4b64f39926fd4c725",
      "kind": "text",
      "outputs": [
        {
          "type": "execute_result",
          "text": "TensorShape([1, 10, 15, 512])"
        }
      ]
    },
    "fcn-the-model-4": {
      "code_fingerprint": "sha256:cfda4c9e7d27c9bb468eb9aff2630880959201664c6530bdc2bd842600e3c747",
      "kind": "text",
      "outputs": [
        {
          "type": "stream",
          "name": "stdout",
          "text": "FCN output shape: (1, 320, 480, 21)\n"
        }
      ]
    },
    "fcn-initializing-transposed-convolutional-layers-1": {
      "code_fingerprint": "sha256:f3746db79b7dc33750fb93cdff430447d1e790ebb70bfc1e1570e18b612987f9",
      "kind": "text",
      "outputs": []
    },
    "fcn-initializing-transposed-convolutional-layers-2": {
      "code_fingerprint": "sha256:f693f12fb7c7db2b9e2690d7ab88b6f6bc7afb875d19717090767ada4f3fb41b",
      "kind": "text",
      "outputs": []
    },
    "fcn-initializing-transposed-convolutional-layers-3": {
      "code_fingerprint": "sha256:5ca799232841ff807594901c0dc62c47c74ed77fc885dd5b9470432fcd2e0f94",
      "kind": "text",
      "outputs": []
    },
    "fcn-initializing-transposed-convolutional-layers-4": {
      "code_fingerprint": "sha256:be68d04f0d17fc3d288e08e1a7b0254e49777f13998ad80d778c43bd9d220889",
      "kind": "mixed",
      "outputs": [
        {
          "type": "stream",
          "name": "stdout",
          "text": "input image shape: (561, 728, 3)\noutput image shape: (1122, 1456, 3)\n"
        },
        {
          "type": "display_data",
          "mime": "image/svg+xml",
          "asset": "fcn/fcn-initializing-transposed-convolutional-layers-4-1.svg",
          "bytes": 86064,
          "sha256": "sha256:8fb710eef6db75252bb786739a6c8268a28f46a952f9964c68a845b4d72e73a9"
        }
      ]
    },
    "fcn-initializing-transposed-convolutional-layers-5": {
      "code_fingerprint": "sha256:7e20ca4741d6b7e627159251914d0ba14cb4ddbd934dbc19aad27630649e9445",
      "kind": "text",
      "outputs": []
    },
    "fcn-reading-the-dataset": {
      "code_fingerprint": "sha256:5ab23c7c8867c9ef501930057fb693687e9d6f6157497b451be800b5fe64401b",
      "kind": "text",
      "outputs": [
        {
          "type": "stream",
          "name": "stdout",
          "text": "read 1114 examples\n"
        },
        {
          "type": "stream",
          "name": "stdout",
          "text": "read 1078 examples\n"
        }
      ]
    },
    "fcn-training": {
      "code_fingerprint": "sha256:fdd9c6a21004502fcd0b013d2c3abdcb81843ea1d0caf7220782d234808bd2ce",
      "kind": "text",
      "outputs": [
        {
          "type": "stream",
          "name": "stdout",
          "text": "Epoch 1/5\n"
        },
        {
          "type": "stream",
          "name": "stdout",
          "text": "\r\u001b[1m 1/34\u001b[0m \u001b[37mв”Ѓв”Ѓв”Ѓв”Ѓв”Ѓв”Ѓв”Ѓв”Ѓв”Ѓв”Ѓв”Ѓв”Ѓв”Ѓв”Ѓв”Ѓв”Ѓв”Ѓв”Ѓв”Ѓв”Ѓ\u001b[0m \u001b[1m18:20\u001b[0m 33s/step - accuracy: 0.0404 - loss: 3.4086"
        },
        {
          "type": "stream",
          "name": "stdout",
          "text": "\b\b\b\b\b\b\b\b\b\b\b\b\b\b\b\b\b\b\b\b\b\b\b\b\b\b\b\b\b\b\b\b\b\b\b\b\b\b\b\b\b\b\b\b\b\b\b\b\b\b\b\b\b\b\b\b\b\b\b\b\b\b\b\b\b\b\b\b\b\b\b\b\b\b\b\r\u001b[1m 2/34\u001b[0m \u001b[32mв”Ѓ\u001b[0m\u001b[37mв”Ѓв”Ѓв”Ѓв”Ѓв”Ѓв”Ѓв”Ѓв”Ѓв”Ѓв”Ѓв”Ѓв”Ѓв”Ѓв”Ѓв”Ѓв”Ѓв”Ѓв”Ѓв”Ѓ\u001b[0m \u001b[1m5s\u001b[0m 163ms/step - accuracy: 0.0446 - loss: 3.3922 "
        },
        {
          "type": "stream",
          "name": "stdout",
          "text": "\b\b\b\b\b\b\b\b\b\b\b\b\b\b\b\b\b\b\b\b\b\b\b\b\b\b\b\b\b\b\b\b\b\b\b\b\b\b\b\b\b\b\b\b\b\b\b\b\b\b\b\b\b\b\b\b\b\b\b\b\b\b\b\b\b\b\b\b\b\b\b\b\b\b\r\u001b[1m 3/34\u001b[0m \u001b[32mв”Ѓ\u001b[0m\u001b[37mв”Ѓв”Ѓв”Ѓв”Ѓв”Ѓв”Ѓв”Ѓв”Ѓв”Ѓв”Ѓв”Ѓв”Ѓв”Ѓв”Ѓв”Ѓв”Ѓв”Ѓв”Ѓв”Ѓ\u001b[0m \u001b[1m5s\u001b[0m 180ms/step - accuracy: 0.0499 - loss: 3.3573"
        },
        {
          "type": "stream",
          "name": "stdout",
          "text": "\b\b\b\b\b\b\b\b\b\b\b\b\b\b\b\b\b\b\b\b\b\b\b\b\b\b\b\b\b\b\b\b\b\b\b\b\b\b\b\b\b\b\b\b\b\b\b\b\b\b\b\b\b\b\b\b\b\b\b\b\b\b\b\b\b\b\b\b\b\b\b\b\b\b\r\u001b[1m 4/34\u001b[0m \u001b[32mв”Ѓв”Ѓ\u001b[0m\u001b[37mв”Ѓв”Ѓв”Ѓв”Ѓв”Ѓв”Ѓв”Ѓв”Ѓв”Ѓв”Ѓв”Ѓв”Ѓв”Ѓв”Ѓв”Ѓв”Ѓв”Ѓв”Ѓ\u001b[0m \u001b[1m5s\u001b[0m 171ms/step - accuracy: 0.0548 - loss: 3.3280"
        },
        {
          "type": "stream",
          "name": "stdout",
          "text": "\b\b\b\b\b\b\b\b\b\b\b\b\b\b\b\b\b\b\b\b\b\b\b\b\b\b\b\b\b\b\b\b\b\b\b\b\b\b\b\b\b\b\b\b\b\b\b\b\b\b\b\b\b\b\b\b\b\b\b\b\b\b\b\b\b\b\b\b\b\b\b\b\b\b\r\u001b[1m 5/34\u001b[0m \u001b[32mв”Ѓв”Ѓ\u001b[0m\u001b[37mв”Ѓв”Ѓв”Ѓв”Ѓв”Ѓв”Ѓв”Ѓв”Ѓв”Ѓв”Ѓв”Ѓв”Ѓв”Ѓв”Ѓв”Ѓв”Ѓв”Ѓв”Ѓ\u001b[0m \u001b[1m4s\u001b[0m 163ms/step - accuracy: 0.0610 - loss: 3.2937"
        },
        {
          "type": "stream",
          "name": "stdout",
          "text": "\b\b\b\b\b\b\b\b\b\b\b\b\b\b\b\b\b\b\b\b\b\b\b\b\b\b\b\b\b\b\b\b\b\b\b\b\b\b\b\b\b\b\b\b\b\b\b\b\b\b\b\b\b\b\b\b\b\b\b\b\b\b\b\b\b\b\b\b\b\b\b\b\b\b\r\u001b[1m 6/34\u001b[0m \u001b[32mв”Ѓв”Ѓв”Ѓ\u001b[0m\u001b[37mв”Ѓв”Ѓв”Ѓв”Ѓв”Ѓв”Ѓв”Ѓв”Ѓв”Ѓв”Ѓв”Ѓв”Ѓв”Ѓв”Ѓв”Ѓв”Ѓв”Ѓ\u001b[0m \u001b[1m4s\u001b[0m 158ms/step - accuracy: 0.0686 - loss: 3.2572"
        },
        {
          "type": "stream",
          "name": "stdout",
          "text": "\b\b\b\b\b\b\b\b\b\b\b\b\b\b\b\b\b\b\b\b\b\b\b\b\b\b\b\b\b\b\b\b\b\b\b\b\b\b\b\b\b\b\b\b\b\b\b\b\b\b\b\b\b\b\b\b\b\b\b\b\b\b\b\b\b\b\b\b\b\b\b\b\b\b\r\u001b[1m 7/34\u001b[0m \u001b[32mв”Ѓв”Ѓв”Ѓв”Ѓ\u001b[0m\u001b[37mв”Ѓв”Ѓв”Ѓв”Ѓв”Ѓв”Ѓв”Ѓв”Ѓв”Ѓв”Ѓв”Ѓв”Ѓв”Ѓв”Ѓв”Ѓв”Ѓ\u001b[0m \u001b[1m4s\u001b[0m 160ms/step - accuracy: 0.0769 - loss: 3.2220"
        },
        {
          "type": "stream",
          "name": "stdout",
          "text": "\b\b\b\b\b\b\b\b\b\b\b\b\b\b\b\b\b\b\b\b\b\b\b\b\b\b\b\b\b\b\b\b\b\b\b\b\b\b\b\b\b\b\b\b\b\b\b\b\b\b\b\b\b\b\b\b\b\b\b\b\b\b\b\b\b\b\b\b\b\b\b\b\b\b\r\u001b[1m 8/34\u001b[0m \u001b[32mв”Ѓв”Ѓв”Ѓв”Ѓ\u001b[0m\u001b[37mв”Ѓв”Ѓв”Ѓв”Ѓв”Ѓв”Ѓв”Ѓв”Ѓв”Ѓв”Ѓв”Ѓв”Ѓв”Ѓв”Ѓв”Ѓв”Ѓ\u001b[0m \u001b[1m5s\u001b[0m 209ms/step - accuracy: 0.0862 - loss: 3.1889"
        },
        {
          "type": "stream",
          "name": "stdout",
          "text": "\b\b\b\b\b\b\b\b\b\b\b\b\b\b\b\b\b\b\b\b\b\b\b\b\b\b\b\b\b\b\b\b\b\b\b\b\b\b\b\b\b\b\b\b\b\b\b\b\b\b\b\b\b\b\b\b\b\b\b\b\b\b\b\b\b\b\b\b\b\b\b\b\b\b\r\u001b[1m 9/34\u001b[0m \u001b[32mв”Ѓв”Ѓв”Ѓв”Ѓв”Ѓ\u001b[0m\u001b[37mв”Ѓв”Ѓв”Ѓв”Ѓв”Ѓв”Ѓв”Ѓв”Ѓв”Ѓв”Ѓв”Ѓв”Ѓв”Ѓв”Ѓв”Ѓ\u001b[0m \u001b[1m5s\u001b[0m 220ms/step - accuracy: 0.0962 - loss: 3.1567"
        },
        {
          "type": "stream",
          "name": "stdout",
          "text": "\b\b\b\b\b\b\b\b\b\b\b\b\b\b\b\b\b\b\b\b\b\b\b\b\b\b\b\b\b\b\b\b\b\b\b\b\b\b\b\b\b\b\b\b\b\b\b\b\b\b\b\b\b\b\b\b\b\b\b\b\b\b\b\b\b\b\b\b\b\b\b\b\b\b\r\u001b[1m10/34\u001b[0m \u001b[32mв”Ѓв”Ѓв”Ѓв”Ѓв”Ѓ\u001b[0m\u001b[37mв”Ѓв”Ѓв”Ѓв”Ѓв”Ѓв”Ѓв”Ѓв”Ѓв”Ѓв”Ѓв”Ѓв”Ѓв”Ѓв”Ѓв”Ѓ\u001b[0m \u001b[1m5s\u001b[0m 226ms/step - accuracy: 0.1069 - loss: 3.1240"
        },
        {
          "type": "stream",
          "name": "stdout",
          "text": "\b\b\b\b\b\b\b\b\b\b\b\b\b\b\b\b\b\b\b\b\b\b\b\b\b\b\b\b\b\b\b\b\b\b\b\b\b\b\b\b\b\b\b\b\b\b\b\b\b\b\b\b\b\b\b\b\b\b\b\b\b\b\b\b\b\b\b\b\b\b\b\b\b\b\r\u001b[1m11/34\u001b[0m \u001b[32mв”Ѓв”Ѓв”Ѓв”Ѓв”Ѓв”Ѓ\u001b[0m\u001b[37mв”Ѓв”Ѓв”Ѓв”Ѓв”Ѓв”Ѓв”Ѓв”Ѓв”Ѓв”Ѓв”Ѓв”Ѓв”Ѓв”Ѓ\u001b[0m \u001b[1m6s\u001b[0m 275ms/step - accuracy: 0.1178 - loss: 3.0917"
        },
        {
          "type": "stream",
          "name": "stdout",
          "text": "\b\b\b\b\b\b\b\b\b\b\b\b\b\b\b\b\b\b\b\b\b\b\b\b\b\b\b\b\b\b\b\b\b\b\b\b\b\b\b\b\b\b\b\b\b\b\b\b\b\b\b\b\b\b\b\b\b\b\b\b\b\b\b\b\b\b\b\b\b\b\b\b\b\b\r\u001b[1m12/34\u001b[0m \u001b[32mв”Ѓв”Ѓв”Ѓв”Ѓв”Ѓв”Ѓв”Ѓ\u001b[0m\u001b[37mв”Ѓв”Ѓв”Ѓв”Ѓв”Ѓв”Ѓв”Ѓв”Ѓв”Ѓв”Ѓв”Ѓв”Ѓв”Ѓ\u001b[0m \u001b[1m6s\u001b[0m 274ms/step - accuracy: 0.1286 - loss: 3.0613"
        },
        {
          "type": "stream",
          "name": "stdout",
          "text": "\b\b\b\b\b\b\b\b\b\b\b\b\b\b\b\b\b\b\b\b\b\b\b\b\b\b\b\b\b\b\b\b\b\b\b\b\b\b\b\b\b\b\b\b\b\b\b\b\b\b\b\b\b\b\b\b\b\b\b\b\b\b\b\b\b\b\b\b\b\b\b\b\b\b\r\u001b[1m13/34\u001b[0m \u001b[32mв”Ѓв”Ѓв”Ѓв”Ѓв”Ѓв”Ѓв”Ѓ\u001b[0m\u001b[37mв”Ѓв”Ѓв”Ѓв”Ѓв”Ѓв”Ѓв”Ѓв”Ѓв”Ѓв”Ѓв”Ѓв”Ѓв”Ѓ\u001b[0m \u001b[1m5s\u001b[0m 266ms/step - accuracy: 0.1393 - loss: 3.0324"
        },
        {
          "type": "stream",
          "name": "stdout",
          "text": "\b\b\b\b\b\b\b\b\b\b\b\b\b\b\b\b\b\b\b\b\b\b\b\b\b\b\b\b\b\b\b\b\b\b\b\b\b\b\b\b\b\b\b\b\b\b\b\b\b\b\b\b\b\b\b\b\b\b\b\b\b\b\b\b\b\b\b\b\b\b\b\b\b\b\r\u001b[1m14/34\u001b[0m \u001b[32mв”Ѓв”Ѓв”Ѓв”Ѓв”Ѓв”Ѓв”Ѓв”Ѓ\u001b[0m\u001b[37mв”Ѓв”Ѓв”Ѓв”Ѓв”Ѓв”Ѓв”Ѓв”Ѓв”Ѓв”Ѓв”Ѓв”Ѓ\u001b[0m \u001b[1m5s\u001b[0m 256ms/step - accuracy: 0.1496 - loss: 3.0050"
        },
        {
          "type": "stream",
          "name": "stdout",
          "text": "\b\b\b\b\b\b\b\b\b\b\b\b\b\b\b\b\b\b\b\b\b\b\b\b\b\b\b\b\b\b\b\b\b\b\b\b\b\b\b\b\b\b\b\b\b\b\b\b\b\b\b\b\b\b\b\b\b\b\b\b\b\b\b\b\b\b\b\b\b\b\b\b\b\b\r\u001b[1m15/34\u001b[0m \u001b[32mв”Ѓв”Ѓв”Ѓв”Ѓв”Ѓв”Ѓв”Ѓв”Ѓ\u001b[0m\u001b[37mв”Ѓв”Ѓв”Ѓв”Ѓв”Ѓв”Ѓв”Ѓв”Ѓв”Ѓв”Ѓв”Ѓв”Ѓ\u001b[0m \u001b[1m4s\u001b[0m 250ms/step - accuracy: 0.1599 - loss: 2.9786"
        },
        {
          "type": "stream",
          "name": "stdout",
          "text": "\b\b\b\b\b\b\b\b\b\b\b\b\b\b\b\b\b\b\b\b\b\b\b\b\b\b\b\b\b\b\b\b\b\b\b\b\b\b\b\b\b\b\b\b\b\b\b\b\b\b\b\b\b\b\b\b\b\b\b\b\b\b\b\b\b\b\b\b\b\b\b\b\b\b\r\u001b[1m16/34\u001b[0m \u001b[32mв”Ѓв”Ѓв”Ѓв”Ѓв”Ѓв”Ѓв”Ѓв”Ѓв”Ѓ\u001b[0m\u001b[37mв”Ѓв”Ѓв”Ѓв”Ѓв”Ѓв”Ѓв”Ѓв”Ѓв”Ѓв”Ѓв”Ѓ\u001b[0m \u001b[1m4s\u001b[0m 244ms/step - accuracy: 0.1701 - loss: 2.9526"
        },
        {
          "type": "stream",
          "name": "stdout",
          "text": "\b\b\b\b\b\b\b\b\b\b\b\b\b\b\b\b\b\b\b\b\b\b\b\b\b\b\b\b\b\b\b\b\b\b\b\b\b\b\b\b\b\b\b\b\b\b\b\b\b\b\b\b\b\b\b\b\b\b\b\b\b\b\b\b\b\b\b\b\b\b\b\b\b\b\r\u001b[1m17/34\u001b[0m \u001b[32mв”Ѓв”Ѓв”Ѓв”Ѓв”Ѓв”Ѓв”Ѓв”Ѓв”Ѓв”Ѓ\u001b[0m\u001b[37mв”Ѓв”Ѓв”Ѓв”Ѓв”Ѓв”Ѓв”Ѓв”Ѓв”Ѓв”Ѓ\u001b[0m \u001b[1m4s\u001b[0m 240ms/step - accuracy: 0.1803 - loss: 2.9263"
        },
        {
          "type": "stream",
          "name": "stdout",
          "text": "\b\b\b\b\b\b\b\b\b\b\b\b\b\b\b\b\b\b\b\b\b\b\b\b\b\b\b\b\b\b\b\b\b\b\b\b\b\b\b\b\b\b\b\b\b\b\b\b\b\b\b\b\b\b\b\b\b\b\b\b\b\b\b\b\b\b\b\b\b\b\b\b\b\b\r\u001b[1m18/34\u001b[0m \u001b[32mв”Ѓв”Ѓв”Ѓв”Ѓв”Ѓв”Ѓв”Ѓв”Ѓв”Ѓв”Ѓ\u001b[0m\u001b[37mв”Ѓв”Ѓв”Ѓв”Ѓв”Ѓв”Ѓв”Ѓв”Ѓв”Ѓв”Ѓ\u001b[0m \u001b[1m3s\u001b[0m 234ms/step - accuracy: 0.1903 - loss: 2.9009"
        },
        {
          "type": "stream",
          "name": "stdout",
          "text": "\b\b\b\b\b\b\b\b\b\b\b\b\b\b\b\b\b\b\b\b\b\b\b\b\b\b\b\b\b\b\b\b\b\b\b\b\b\b\b\b\b\b\b\b\b\b\b\b\b\b\b\b\b\b\b\b\b\b\b\b\b\b\b\b\b\b\b\b\b\b\b\b\b\b\r\u001b[1m19/34\u001b[0m \u001b[32mв”Ѓв”Ѓв”Ѓв”Ѓв”Ѓв”Ѓв”Ѓв”Ѓв”Ѓв”Ѓв”Ѓ\u001b[0m\u001b[37mв”Ѓв”Ѓв”Ѓв”Ѓв”Ѓв”Ѓв”Ѓв”Ѓв”Ѓ\u001b[0m \u001b[1m3s\u001b[0m 231ms/step - accuracy: 0.2000 - loss: 2.8763"
        },
        {
          "type": "stream",
          "name": "stdout",
          "text": "\b\b\b\b\b\b\b\b\b\b\b\b\b\b\b\b\b\b\b\b\b\b\b\b\b\b\b\b\b\b\b\b\b\b\b\b\b\b\b\b\b\b\b\b\b\b\b\b\b\b\b\b\b\b\b\b\b\b\b\b\b\b\b\b\b\b\b\b\b\b\b\b\b\b\r\u001b[1m20/34\u001b[0m \u001b[32mв”Ѓв”Ѓв”Ѓв”Ѓв”Ѓв”Ѓв”Ѓв”Ѓв”Ѓв”Ѓв”Ѓ\u001b[0m\u001b[37mв”Ѓв”Ѓв”Ѓв”Ѓв”Ѓв”Ѓв”Ѓв”Ѓв”Ѓ\u001b[0m \u001b[1m3s\u001b[0m 228ms/step - accuracy: 0.2094 - loss: 2.8527"
        },
        {
          "type": "stream",
          "name": "stdout",
          "text": "\b\b\b\b\b\b\b\b\b\b\b\b\b\b\b\b\b\b\b\b\b\b\b\b\b\b\b\b\b\b\b\b\b\b\b\b\b\b\b\b\b\b\b\b\b\b\b\b\b\b\b\b\b\b\b\b\b\b\b\b\b\b\b\b\b\b\b\b\b\b\b\b\b\b\r\u001b[1m21/34\u001b[0m \u001b[32mв”Ѓв”Ѓв”Ѓв”Ѓв”Ѓв”Ѓв”Ѓв”Ѓв”Ѓв”Ѓв”Ѓв”Ѓ\u001b[0m\u001b[37mв”Ѓв”Ѓв”Ѓв”Ѓв”Ѓв”Ѓв”Ѓв”Ѓ\u001b[0m \u001b[1m2s\u001b[0m 225ms/step - accuracy: 0.2184 - loss: 2.8305"
        },
        {
          "type": "stream",
          "name": "stdout",
          "text": "\b\b\b\b\b\b\b\b\b\b\b\b\b\b\b\b\b\b\b\b\b\b\b\b\b\b\b\b\b\b\b\b\b\b\b\b\b\b\b\b\b\b\b\b\b\b\b\b\b\b\b\b\b\b\b\b\b\b\b\b\b\b\b\b\b\b\b\b\b\b\b\b\b\b\r\u001b[1m22/34\u001b[0m \u001b[32mв”Ѓв”Ѓв”Ѓв”Ѓв”Ѓв”Ѓв”Ѓв”Ѓв”Ѓв”Ѓв”Ѓв”Ѓ\u001b[0m\u001b[37mв”Ѓв”Ѓв”Ѓв”Ѓв”Ѓв”Ѓв”Ѓв”Ѓ\u001b[0m \u001b[1m2s\u001b[0m 222ms/step - accuracy: 0.2271 - loss: 2.8088"
        },
        {
          "type": "stream",
          "name": "stdout",
          "text": "\b\b\b\b\b\b\b\b\b\b\b\b\b\b\b\b\b\b\b\b\b\b\b\b\b\b\b\b\b\b\b\b\b\b\b\b\b\b\b\b\b\b\b\b\b\b\b\b\b\b\b\b\b\b\b\b\b\b\b\b\b\b\b\b\b\b\b\b\b\b\b\b\b\b\r\u001b[1m23/34\u001b[0m \u001b[32mв”Ѓв”Ѓв”Ѓв”Ѓв”Ѓв”Ѓв”Ѓв”Ѓв”Ѓв”Ѓв”Ѓв”Ѓв”Ѓ\u001b[0m\u001b[37mв”Ѓв”Ѓв”Ѓв”Ѓв”Ѓв”Ѓв”Ѓ\u001b[0m \u001b[1m2s\u001b[0m 219ms/step - accuracy: 0.2356 - loss: 2.7878"
        },
        {
          "type": "stream",
          "name": "stdout",
          "text": "\b\b\b\b\b\b\b\b\b\b\b\b\b\b\b\b\b\b\b\b\b\b\b\b\b\b\b\b\b\b\b\b\b\b\b\b\b\b\b\b\b\b\b\b\b\b\b\b\b\b\b\b\b\b\b\b\b\b\b\b\b\b\b\b\b\b\b\b\b\b\b\b\b\b\r\u001b[1m24/34\u001b[0m \u001b[32mв”Ѓв”Ѓв”Ѓв”Ѓв”Ѓв”Ѓв”Ѓв”Ѓв”Ѓв”Ѓв”Ѓв”Ѓв”Ѓв”Ѓ\u001b[0m\u001b[37mв”Ѓв”Ѓв”Ѓв”Ѓв”Ѓв”Ѓ\u001b[0m \u001b[1m2s\u001b[0m 215ms/step - accuracy: 0.2440 - loss: 2.7670"
        },
        {
          "type": "stream",
          "name": "stdout",
          "text": "\b\b\b\b\b\b\b\b\b\b\b\b\b\b\b\b\b\b\b\b\b\b\b\b\b\b\b\b\b\b\b\b\b\b\b\b\b\b\b\b\b\b\b\b\b\b\b\b\b\b\b\b\b\b\b\b\b\b\b\b\b\b\b\b\b\b\b\b\b\b\b\b\b\b\r\u001b[1m25/34\u001b[0m \u001b[32mв”Ѓв”Ѓв”Ѓв”Ѓв”Ѓв”Ѓв”Ѓв”Ѓв”Ѓв”Ѓв”Ѓв”Ѓв”Ѓв”Ѓ\u001b[0m\u001b[37mв”Ѓв”Ѓв”Ѓв”Ѓв”Ѓв”Ѓ\u001b[0m \u001b[1m1s\u001b[0m 214ms/step - accuracy: 0.2521 - loss: 2.7466"
        },
        {
          "type": "stream",
          "name": "stdout",
          "text": "\b\b\b\b\b\b\b\b\b\b\b\b\b\b\b\b\b\b\b\b\b\b\b\b\b\b\b\b\b\b\b\b\b\b\b\b\b\b\b\b\b\b\b\b\b\b\b\b\b\b\b\b\b\b\b\b\b\b\b\b\b\b\b\b\b\b\b\b\b\b\b\b\b\b\r\u001b[1m26/34\u001b[0m \u001b[32mв”Ѓв”Ѓв”Ѓв”Ѓв”Ѓв”Ѓв”Ѓв”Ѓв”Ѓв”Ѓв”Ѓв”Ѓв”Ѓв”Ѓв”Ѓ\u001b[0m\u001b[37mв”Ѓв”Ѓв”Ѓв”Ѓв”Ѓ\u001b[0m \u001b[1m1s\u001b[0m 212ms/step - accuracy: 0.2600 - loss: 2.7267"
        },
        {
          "type": "stream",
          "name": "stdout",
          "text": "\b\b\b\b\b\b\b\b\b\b\b\b\b\b\b\b\b\b\b\b\b\b\b\b\b\b\b\b\b\b\b\b\b\b\b\b\b\b\b\b\b\b\b\b\b\b\b\b\b\b\b\b\b\b\b\b\b\b\b\b\b\b\b\b\b\b\b\b\b\b\b\b\b\b\r\u001b[1m27/34\u001b[0m \u001b[32mв”Ѓв”Ѓв”Ѓв”Ѓв”Ѓв”Ѓв”Ѓв”Ѓв”Ѓв”Ѓв”Ѓв”Ѓв”Ѓв”Ѓв”Ѓ\u001b[0m\u001b[37mв”Ѓв”Ѓв”Ѓв”Ѓв”Ѓ\u001b[0m \u001b[1m1s\u001b[0m 209ms/step - accuracy: 0.2677 - loss: 2.7076"
        },
        {
          "type": "stream",
          "name": "stdout",
          "text": "\b\b\b\b\b\b\b\b\b\b\b\b\b\b\b\b\b\b\b\b\b\b\b\b\b\b\b\b\b\b\b\b\b\b\b\b\b\b\b\b\b\b\b\b\b\b\b\b\b\b\b\b\b\b\b\b\b\b\b\b\b\b\b\b\b\b\b\b\b\b\b\b\b\b\r\u001b[1m28/34\u001b[0m \u001b[32mв”Ѓв”Ѓв”Ѓв”Ѓв”Ѓв”Ѓв”Ѓв”Ѓв”Ѓв”Ѓв”Ѓв”Ѓв”Ѓв”Ѓв”Ѓв”Ѓ\u001b[0m\u001b[37mв”Ѓв”Ѓв”Ѓв”Ѓ\u001b[0m \u001b[1m1s\u001b[0m 206ms/step - accuracy: 0.2750 - loss: 2.6891"
        },
        {
          "type": "stream",
          "name": "stdout",
          "text": "\b\b\b\b\b\b\b\b\b\b\b\b\b\b\b\b\b\b\b\b\b\b\b\b\b\b\b\b\b\b\b\b\b\b\b\b\b\b\b\b\b\b\b\b\b\b\b\b\b\b\b\b\b\b\b\b\b\b\b\b\b\b\b\b\b\b\b\b\b\b\b\b\b\b\r\u001b[1m29/34\u001b[0m \u001b[32mв”Ѓв”Ѓв”Ѓв”Ѓв”Ѓв”Ѓв”Ѓв”Ѓв”Ѓв”Ѓв”Ѓв”Ѓв”Ѓв”Ѓв”Ѓв”Ѓв”Ѓ\u001b[0m\u001b[37mв”Ѓв”Ѓв”Ѓ\u001b[0m \u001b[1m1s\u001b[0m 202ms/step - accuracy: 0.2821 - loss: 2.6715"
        },
        {
          "type": "stream",
          "name": "stdout",
          "text": "\b\b\b\b\b\b\b\b\b\b\b\b\b\b\b\b\b\b\b\b\b\b\b\b\b\b\b\b\b\b\b\b\b\b\b\b\b\b\b\b\b\b\b\b\b\b\b\b\b\b\b\b\b\b\b\b\b\b\b\b\b\b\b\b\b\b\b\b\b\b\b\b\b\b\r\u001b[1m30/34\u001b[0m \u001b[32mв”Ѓв”Ѓв”Ѓв”Ѓв”Ѓв”Ѓв”Ѓв”Ѓв”Ѓв”Ѓв”Ѓв”Ѓв”Ѓв”Ѓв”Ѓв”Ѓв”Ѓ\u001b[0m\u001b[37mв”Ѓв”Ѓв”Ѓ\u001b[0m \u001b[1m0s\u001b[0m 199ms/step - accuracy: 0.2889 - loss: 2.6545"
        },
        {
          "type": "stream",
          "name": "stdout",
          "text": "\b\b\b\b\b\b\b\b\b\b\b\b\b\b\b\b\b\b\b\b\b\b\b\b\b\b\b\b\b\b\b\b\b\b\b\b\b\b\b\b\b\b\b\b\b\b\b\b\b\b\b\b\b\b\b\b\b\b\b\b\b\b\b\b\b\b\b\b\b\b\b\b\b\b\r\u001b[1m31/34\u001b[0m \u001b[32mв”Ѓв”Ѓв”Ѓв”Ѓв”Ѓв”Ѓв”Ѓв”Ѓв”Ѓв”Ѓв”Ѓв”Ѓв”Ѓв”Ѓв”Ѓв”Ѓв”Ѓв”Ѓ\u001b[0m\u001b[37mв”Ѓв”Ѓ\u001b[0m \u001b[1m0s\u001b[0m 196ms/step - accuracy: 0.2955 - loss: 2.6381"
        },
        {
          "type": "stream",
          "name": "stdout",
          "text": "\b\b\b\b\b\b\b\b\b\b\b\b\b\b\b\b\b\b\b\b\b\b\b\b\b\b\b\b\b\b\b\b\b\b\b\b\b\b\b\b\b\b\b\b\b\b\b\b\b\b\b\b\b\b\b\b\b\b\b\b\b\b\b\b\b\b\b\b\b\b\b\b\b\b\r\u001b[1m32/34\u001b[0m \u001b[32mв”Ѓв”Ѓв”Ѓв”Ѓв”Ѓв”Ѓв”Ѓв”Ѓв”Ѓв”Ѓв”Ѓв”Ѓв”Ѓв”Ѓв”Ѓв”Ѓв”Ѓв”Ѓ\u001b[0m\u001b[37mв”Ѓв”Ѓ\u001b[0m \u001b[1m0s\u001b[0m 193ms/step - accuracy: 0.3019 - loss: 2.6220"
        },
        {
          "type": "stream",
          "name": "stdout",
          "text": "\b\b\b\b\b\b\b\b\b\b\b\b\b\b\b\b\b\b\b\b\b\b\b\b\b\b\b\b\b\b\b\b\b\b\b\b\b\b\b\b\b\b\b\b\b\b\b\b\b\b\b\b\b\b\b\b\b\b\b\b\b\b\b\b\b\b\b\b\b\b\b\b\b\b\r\u001b[1m33/34\u001b[0m \u001b[32mв”Ѓв”Ѓв”Ѓв”Ѓв”Ѓв”Ѓв”Ѓв”Ѓв”Ѓв”Ѓв”Ѓв”Ѓв”Ѓв”Ѓв”Ѓв”Ѓв”Ѓв”Ѓв”Ѓ\u001b[0m\u001b[37mв”Ѓ\u001b[0m \u001b[1m0s\u001b[0m 190ms/step - accuracy: 0.3081 - loss: 2.6064"
        },
        {
          "type": "stream",
          "name": "stdout",
          "text": "\b\b\b\b\b\b\b\b\b\b\b\b\b\b\b\b\b\b\b\b\b\b\b\b\b\b\b\b\b\b\b\b\b\b\b\b\b\b\b\b\b\b\b\b\b\b\b\b\b\b\b\b\b\b\b\b\b\b\b\b\b\b\b\b\b\b\b\b\b\b\b\b\b\b\r\u001b[1m34/34\u001b[0m \u001b[32mв”Ѓв”Ѓв”Ѓв”Ѓв”Ѓв”Ѓв”Ѓв”Ѓв”Ѓв”Ѓв”Ѓв”Ѓв”Ѓв”Ѓв”Ѓв”Ѓв”Ѓв”Ѓв”Ѓв”Ѓ\u001b[0m\u001b[37m\u001b[0m \u001b[1m0s\u001b[0m 187ms/step - accuracy: 0.3141 - loss: 2.5912"
        },
        {
          "type": "stream",
          "name": "stdout",
          "text": "\b\b\b\b\b\b\b\b\b\b\b\b\b\b\b\b\b\b\b\b\b\b\b\b\b\b\b\b\b\b\b\b\b\b\b\b\b\b\b\b\b\b\b\b\b\b\b\b\b\b\b\b\b\b\b\b\b\b\b\b\b\b\b\b\b\b\b\b\b\b\b\b\b\b\r\u001b[1m34/34\u001b[0m \u001b[32mв”Ѓв”Ѓв”Ѓв”Ѓв”Ѓв”Ѓв”Ѓв”Ѓв”Ѓв”Ѓв”Ѓв”Ѓв”Ѓв”Ѓв”Ѓв”Ѓв”Ѓв”Ѓв”Ѓв”Ѓ\u001b[0m\u001b[37m\u001b[0m \u001b[1m47s\u001b[0m 413ms/step - accuracy: 0.5124 - loss: 2.0905 - val_accuracy: 0.7274 - val_loss: 2.5202\n"
        },
        {
          "type": "stream",
          "name": "stdout",
          "text": "Epoch 2/5\n"
        },
        {
          "type": "stream",
          "name": "stdout",
          "text": "\r\u001b[1m 1/34\u001b[0m \u001b[37mв”Ѓв”Ѓв”Ѓв”Ѓв”Ѓв”Ѓв”Ѓв”Ѓв”Ѓв”Ѓв”Ѓв”Ѓв”Ѓв”Ѓв”Ѓв”Ѓв”Ѓв”Ѓв”Ѓв”Ѓ\u001b[0m \u001b[1m11s\u001b[0m 335ms/step - accuracy: 0.7042 - loss: 1.5869"
        },
        {
          "type": "stream",
          "name": "stdout",
          "text": "\b\b\b\b\b\b\b\b\b\b\b\b\b\b\b\b\b\b\b\b\b\b\b\b\b\b\b\b\b\b\b\b\b\b\b\b\b\b\b\b\b\b\b\b\b\b\b\b\b\b\b\b\b\b\b\b\b\b\b\b\b\b\b\b\b\b\b\b\b\b\b\b\b\b\b\r\u001b[1m 2/34\u001b[0m \u001b[32mв”Ѓ\u001b[0m\u001b[37mв”Ѓв”Ѓв”Ѓв”Ѓв”Ѓв”Ѓв”Ѓв”Ѓв”Ѓв”Ѓв”Ѓв”Ѓв”Ѓв”Ѓв”Ѓв”Ѓв”Ѓв”Ѓв”Ѓ\u001b[0m \u001b[1m12s\u001b[0m 381ms/step - accuracy: 0.6957 - loss: 1.6233"
        },
        {
          "type": "stream",
          "name": "stdout",
          "text": "\b\b\b\b\b\b\b\b\b\b\b\b\b\b\b\b\b\b\b\b\b\b\b\b\b\b\b\b\b\b\b\b\b\b\b\b\b\b\b\b\b\b\b\b\b\b\b\b\b\b\b\b\b\b\b\b\b\b\b\b\b\b\b\b\b\b\b\b\b\b\b\b\b\b\b\r\u001b[1m 3/34\u001b[0m \u001b[32mв”Ѓ\u001b[0m\u001b[37mв”Ѓв”Ѓв”Ѓв”Ѓв”Ѓв”Ѓв”Ѓв”Ѓв”Ѓв”Ѓв”Ѓв”Ѓв”Ѓв”Ѓв”Ѓв”Ѓв”Ѓв”Ѓв”Ѓ\u001b[0m \u001b[1m8s\u001b[0m 289ms/step - accuracy: 0.6944 - loss: 1.6268 "
        },
        {
          "type": "stream",
          "name": "stdout",
          "text": "\b\b\b\b\b\b\b\b\b\b\b\b\b\b\b\b\b\b\b\b\b\b\b\b\b\b\b\b\b\b\b\b\b\b\b\b\b\b\b\b\b\b\b\b\b\b\b\b\b\b\b\b\b\b\b\b\b\b\b\b\b\b\b\b\b\b\b\b\b\b\b\b\b\b\r\u001b[1m 4/34\u001b[0m \u001b[32mв”Ѓв”Ѓ\u001b[0m\u001b[37mв”Ѓв”Ѓв”Ѓв”Ѓв”Ѓв”Ѓв”Ѓв”Ѓв”Ѓв”Ѓв”Ѓв”Ѓв”Ѓв”Ѓв”Ѓв”Ѓв”Ѓв”Ѓ\u001b[0m \u001b[1m8s\u001b[0m 285ms/step - accuracy: 0.6982 - loss: 1.6080"
        },
        {
          "type": "stream",
          "name": "stdout",
          "text": "\b\b\b\b\b\b\b\b\b\b\b\b\b\b\b\b\b\b\b\b\b\b\b\b\b\b\b\b\b\b\b\b\b\b\b\b\b\b\b\b\b\b\b\b\b\b\b\b\b\b\b\b\b\b\b\b\b\b\b\b\b\b\b\b\b\b\b\b\b\b\b\b\b\b\r\u001b[1m 5/34\u001b[0m \u001b[32mв”Ѓв”Ѓ\u001b[0m\u001b[37mв”Ѓв”Ѓв”Ѓв”Ѓв”Ѓв”Ѓв”Ѓв”Ѓв”Ѓв”Ѓв”Ѓв”Ѓв”Ѓв”Ѓв”Ѓв”Ѓв”Ѓв”Ѓ\u001b[0m \u001b[1m7s\u001b[0m 273ms/step - accuracy: 0.7003 - loss: 1.6008"
        },
        {
          "type": "stream",
          "name": "stdout",
          "text": "\b\b\b\b\b\b\b\b\b\b\b\b\b\b\b\b\b\b\b\b\b\b\b\b\b\b\b\b\b\b\b\b\b\b\b\b\b\b\b\b\b\b\b\b\b\b\b\b\b\b\b\b\b\b\b\b\b\b\b\b\b\b\b\b\b\b\b\b\b\b\b\b\b\b\r\u001b[1m 6/34\u001b[0m \u001b[32mв”Ѓв”Ѓв”Ѓ\u001b[0m\u001b[37mв”Ѓв”Ѓв”Ѓв”Ѓв”Ѓв”Ѓв”Ѓв”Ѓв”Ѓв”Ѓв”Ѓв”Ѓв”Ѓв”Ѓв”Ѓв”Ѓв”Ѓ\u001b[0m \u001b[1m6s\u001b[0m 247ms/step - accuracy: 0.7009 - loss: 1.5998"
        },
        {
          "type": "stream",
          "name": "stdout",
          "text": "\b\b\b\b\b\b\b\b\b\b\b\b\b\b\b\b\b\b\b\b\b\b\b\b\b\b\b\b\b\b\b\b\b\b\b\b\b\b\b\b\b\b\b\b\b\b\b\b\b\b\b\b\b\b\b\b\b\b\b\b\b\b\b\b\b\b\b\b\b\b\b\b\b\b\r\u001b[1m 7/34\u001b[0m \u001b[32mв”Ѓв”Ѓв”Ѓв”Ѓ\u001b[0m\u001b[37mв”Ѓв”Ѓв”Ѓв”Ѓв”Ѓв”Ѓв”Ѓв”Ѓв”Ѓв”Ѓв”Ѓв”Ѓв”Ѓв”Ѓв”Ѓв”Ѓ\u001b[0m \u001b[1m6s\u001b[0m 237ms/step - accuracy: 0.7013 - loss: 1.5983"
        },
        {
          "type": "stream",
          "name": "stdout",
          "text": "\b\b\b\b\b\b\b\b\b\b\b\b\b\b\b\b\b\b\b\b\b\b\b\b\b\b\b\b\b\b\b\b\b\b\b\b\b\b\b\b\b\b\b\b\b\b\b\b\b\b\b\b\b\b\b\b\b\b\b\b\b\b\b\b\b\b\b\b\b\b\b\b\b\b\r\u001b[1m 8/34\u001b[0m \u001b[32mв”Ѓв”Ѓв”Ѓв”Ѓ\u001b[0m\u001b[37mв”Ѓв”Ѓв”Ѓв”Ѓв”Ѓв”Ѓв”Ѓв”Ѓв”Ѓв”Ѓв”Ѓв”Ѓв”Ѓв”Ѓв”Ѓв”Ѓ\u001b[0m \u001b[1m5s\u001b[0m 230ms/step - accuracy: 0.7011 - loss: 1.6013"
        },
        {
          "type": "stream",
          "name": "stdout",
          "text": "\b\b\b\b\b\b\b\b\b\b\b\b\b\b\b\b\b\b\b\b\b\b\b\b\b\b\b\b\b\b\b\b\b\b\b\b\b\b\b\b\b\b\b\b\b\b\b\b\b\b\b\b\b\b\b\b\b\b\b\b\b\b\b\b\b\b\b\b\b\b\b\b\b\b\r\u001b[1m 9/34\u001b[0m \u001b[32mв”Ѓв”Ѓв”Ѓв”Ѓв”Ѓ\u001b[0m\u001b[37mв”Ѓв”Ѓв”Ѓв”Ѓв”Ѓв”Ѓв”Ѓв”Ѓв”Ѓв”Ѓв”Ѓв”Ѓв”Ѓв”Ѓв”Ѓ\u001b[0m \u001b[1m5s\u001b[0m 218ms/step - accuracy: 0.7015 - loss: 1.6014"
        },
        {
          "type": "stream",
          "name": "stdout",
          "text": "\b\b\b\b\b\b\b\b\b\b\b\b\b\b\b\b\b\b\b\b\b\b\b\b\b\b\b\b\b\b\b\b\b\b\b\b\b\b\b\b\b\b\b\b\b\b\b\b\b\b\b\b\b\b\b\b\b\b\b\b\b\b\b\b\b\b\b\b\b\b\b\b\b\b\r\u001b[1m10/34\u001b[0m \u001b[32mв”Ѓв”Ѓв”Ѓв”Ѓв”Ѓ\u001b[0m\u001b[37mв”Ѓв”Ѓв”Ѓв”Ѓв”Ѓв”Ѓв”Ѓв”Ѓв”Ѓв”Ѓв”Ѓв”Ѓв”Ѓв”Ѓв”Ѓ\u001b[0m \u001b[1m5s\u001b[0m 211ms/step - accuracy: 0.7014 - loss: 1.6032"
        },
        {
          "type": "stream",
          "name": "stdout",
          "text": "\b\b\b\b\b\b\b\b\b\b\b\b\b\b\b\b\b\b\b\b\b\b\b\b\b\b\b\b\b\b\b\b\b\b\b\b\b\b\b\b\b\b\b\b\b\b\b\b\b\b\b\b\b\b\b\b\b\b\b\b\b\b\b\b\b\b\b\b\b\b\b\b\b\b\r\u001b[1m11/34\u001b[0m \u001b[32mв”Ѓв”Ѓв”Ѓв”Ѓв”Ѓв”Ѓ\u001b[0m\u001b[37mв”Ѓв”Ѓв”Ѓв”Ѓв”Ѓв”Ѓв”Ѓв”Ѓв”Ѓв”Ѓв”Ѓв”Ѓв”Ѓв”Ѓ\u001b[0m \u001b[1m4s\u001b[0m 210ms/step - accuracy: 0.7014 - loss: 1.6043"
        },
        {
          "type": "stream",
          "name": "stdout",
          "text": "\b\b\b\b\b\b\b\b\b\b\b\b\b\b\b\b\b\b\b\b\b\b\b\b\b\b\b\b\b\b\b\b\b\b\b\b\b\b\b\b\b\b\b\b\b\b\b\b\b\b\b\b\b\b\b\b\b\b\b\b\b\b\b\b\b\b\b\b\b\b\b\b\b\b\r\u001b[1m12/34\u001b[0m \u001b[32mв”Ѓв”Ѓв”Ѓв”Ѓв”Ѓв”Ѓв”Ѓ\u001b[0m\u001b[37mв”Ѓв”Ѓв”Ѓв”Ѓв”Ѓв”Ѓв”Ѓв”Ѓв”Ѓв”Ѓв”Ѓв”Ѓв”Ѓ\u001b[0m \u001b[1m4s\u001b[0m 206ms/step - accuracy: 0.7014 - loss: 1.6045"
        },
        {
          "type": "stream",
          "name": "stdout",
          "text": "\b\b\b\b\b\b\b\b\b\b\b\b\b\b\b\b\b\b\b\b\b\b\b\b\b\b\b\b\b\b\b\b\b\b\b\b\b\b\b\b\b\b\b\b\b\b\b\b\b\b\b\b\b\b\b\b\b\b\b\b\b\b\b\b\b\b\b\b\b\b\b\b\b\b\r\u001b[1m13/34\u001b[0m \u001b[32mв”Ѓв”Ѓв”Ѓв”Ѓв”Ѓв”Ѓв”Ѓ\u001b[0m\u001b[37mв”Ѓв”Ѓв”Ѓв”Ѓв”Ѓв”Ѓв”Ѓв”Ѓв”Ѓв”Ѓв”Ѓв”Ѓв”Ѓ\u001b[0m \u001b[1m4s\u001b[0m 202ms/step - accuracy: 0.7015 - loss: 1.6040"
        },
        {
          "type": "stream",
          "name": "stdout",
          "text": "\b\b\b\b\b\b\b\b\b\b\b\b\b\b\b\b\b\b\b\b\b\b\b\b\b\b\b\b\b\b\b\b\b\b\b\b\b\b\b\b\b\b\b\b\b\b\b\b\b\b\b\b\b\b\b\b\b\b\b\b\b\b\b\b\b\b\b\b\b\b\b\b\b\b\r\u001b[1m14/34\u001b[0m \u001b[32mв”Ѓв”Ѓв”Ѓв”Ѓв”Ѓв”Ѓв”Ѓв”Ѓ\u001b[0m\u001b[37mв”Ѓв”Ѓв”Ѓв”Ѓв”Ѓв”Ѓв”Ѓв”Ѓв”Ѓв”Ѓв”Ѓв”Ѓ\u001b[0m \u001b[1m3s\u001b[0m 200ms/step - accuracy: 0.7019 - loss: 1.6024"
        },
        {
          "type": "stream",
          "name": "stdout",
          "text": "\b\b\b\b\b\b\b\b\b\b\b\b\b\b\b\b\b\b\b\b\b\b\b\b\b\b\b\b\b\b\b\b\b\b\b\b\b\b\b\b\b\b\b\b\b\b\b\b\b\b\b\b\b\b\b\b\b\b\b\b\b\b\b\b\b\b\b\b\b\b\b\b\b\b\r\u001b[1m15/34\u001b[0m \u001b[32mв”Ѓв”Ѓв”Ѓв”Ѓв”Ѓв”Ѓв”Ѓв”Ѓ\u001b[0m\u001b[37mв”Ѓв”Ѓв”Ѓв”Ѓв”Ѓв”Ѓв”Ѓв”Ѓв”Ѓв”Ѓв”Ѓв”Ѓ\u001b[0m \u001b[1m3s\u001b[0m 195ms/step - accuracy: 0.7022 - loss: 1.6009"
        },
        {
          "type": "stream",
          "name": "stdout",
          "text": "\b\b\b\b\b\b\b\b\b\b\b\b\b\b\b\b\b\b\b\b\b\b\b\b\b\b\b\b\b\b\b\b\b\b\b\b\b\b\b\b\b\b\b\b\b\b\b\b\b\b\b\b\b\b\b\b\b\b\b\b\b\b\b\b\b\b\b\b\b\b\b\b\b\b\r\u001b[1m16/34\u001b[0m \u001b[32mв”Ѓв”Ѓв”Ѓв”Ѓв”Ѓв”Ѓв”Ѓв”Ѓв”Ѓ\u001b[0m\u001b[37mв”Ѓв”Ѓв”Ѓв”Ѓв”Ѓв”Ѓв”Ѓв”Ѓв”Ѓв”Ѓв”Ѓ\u001b[0m \u001b[1m3s\u001b[0m 192ms/step - accuracy: 0.7026 - loss: 1.5991"
        },
        {
          "type": "stream",
          "name": "stdout",
          "text": "\b\b\b\b\b\b\b\b\b\b\b\b\b\b\b\b\b\b\b\b\b\b\b\b\b\b\b\b\b\b\b\b\b\b\b\b\b\b\b\b\b\b\b\b\b\b\b\b\b\b\b\b\b\b\b\b\b\b\b\b\b\b\b\b\b\b\b\b\b\b\b\b\b\b\r\u001b[1m17/34\u001b[0m \u001b[32mв”Ѓв”Ѓв”Ѓв”Ѓв”Ѓв”Ѓв”Ѓв”Ѓв”Ѓв”Ѓ\u001b[0m\u001b[37mв”Ѓв”Ѓв”Ѓв”Ѓв”Ѓв”Ѓв”Ѓв”Ѓв”Ѓв”Ѓ\u001b[0m \u001b[1m3s\u001b[0m 190ms/step - accuracy: 0.7028 - loss: 1.5983"
        },
        {
          "type": "stream",
          "name": "stdout",
          "text": "\b\b\b\b\b\b\b\b\b\b\b\b\b\b\b\b\b\b\b\b\b\b\b\b\b\b\b\b\b\b\b\b\b\b\b\b\b\b\b\b\b\b\b\b\b\b\b\b\b\b\b\b\b\b\b\b\b\b\b\b\b\b\b\b\b\b\b\b\b\b\b\b\b\b\r\u001b[1m18/34\u001b[0m \u001b[32mв”Ѓв”Ѓв”Ѓв”Ѓв”Ѓв”Ѓв”Ѓв”Ѓв”Ѓв”Ѓ\u001b[0m\u001b[37mв”Ѓв”Ѓв”Ѓв”Ѓв”Ѓв”Ѓв”Ѓв”Ѓв”Ѓв”Ѓ\u001b[0m \u001b[1m2s\u001b[0m 187ms/step - accuracy: 0.7030 - loss: 1.5969"
        },
        {
          "type": "stream",
          "name": "stdout",
          "text": "\b\b\b\b\b\b\b\b\b\b\b\b\b\b\b\b\b\b\b\b\b\b\b\b\b\b\b\b\b\b\b\b\b\b\b\b\b\b\b\b\b\b\b\b\b\b\b\b\b\b\b\b\b\b\b\b\b\b\b\b\b\b\b\b\b\b\b\b\b\b\b\b\b\b\r\u001b[1m19/34\u001b[0m \u001b[32mв”Ѓв”Ѓв”Ѓв”Ѓв”Ѓв”Ѓв”Ѓв”Ѓв”Ѓв”Ѓв”Ѓ\u001b[0m\u001b[37mв”Ѓв”Ѓв”Ѓв”Ѓв”Ѓв”Ѓв”Ѓв”Ѓв”Ѓ\u001b[0m \u001b[1m2s\u001b[0m 186ms/step - accuracy: 0.7030 - loss: 1.5961"
        },
        {
          "type": "stream",
          "name": "stdout",
          "text": "\b\b\b\b\b\b\b\b\b\b\b\b\b\b\b\b\b\b\b\b\b\b\b\b\b\b\b\b\b\b\b\b\b\b\b\b\b\b\b\b\b\b\b\b\b\b\b\b\b\b\b\b\b\b\b\b\b\b\b\b\b\b\b\b\b\b\b\b\b\b\b\b\b\b\r\u001b[1m20/34\u001b[0m \u001b[32mв”Ѓв”Ѓв”Ѓв”Ѓв”Ѓв”Ѓв”Ѓв”Ѓв”Ѓв”Ѓв”Ѓ\u001b[0m\u001b[37mв”Ѓв”Ѓв”Ѓв”Ѓв”Ѓв”Ѓв”Ѓв”Ѓв”Ѓ\u001b[0m \u001b[1m2s\u001b[0m 185ms/step - accuracy: 0.7031 - loss: 1.5952"
        },
        {
          "type": "stream",
          "name": "stdout",
          "text": "\b\b\b\b\b\b\b\b\b\b\b\b\b\b\b\b\b\b\b\b\b\b\b\b\b\b\b\b\b\b\b\b\b\b\b\b\b\b\b\b\b\b\b\b\b\b\b\b\b\b\b\b\b\b\b\b\b\b\b\b\b\b\b\b\b\b\b\b\b\b\b\b\b\b\r\u001b[1m21/34\u001b[0m \u001b[32mв”Ѓв”Ѓв”Ѓв”Ѓв”Ѓв”Ѓв”Ѓв”Ѓв”Ѓв”Ѓв”Ѓв”Ѓ\u001b[0m\u001b[37mв”Ѓв”Ѓв”Ѓв”Ѓв”Ѓв”Ѓв”Ѓв”Ѓ\u001b[0m \u001b[1m2s\u001b[0m 185ms/step - accuracy: 0.7033 - loss: 1.5938"
        },
        {
          "type": "stream",
          "name": "stdout",
          "text": "\b\b\b\b\b\b\b\b\b\b\b\b\b\b\b\b\b\b\b\b\b\b\b\b\b\b\b\b\b\b\b\b\b\b\b\b\b\b\b\b\b\b\b\b\b\b\b\b\b\b\b\b\b\b\b\b\b\b\b\b\b\b\b\b\b\b\b\b\b\b\b\b\b\b\r\u001b[1m22/34\u001b[0m \u001b[32mв”Ѓв”Ѓв”Ѓв”Ѓв”Ѓв”Ѓв”Ѓв”Ѓв”Ѓв”Ѓв”Ѓв”Ѓ\u001b[0m\u001b[37mв”Ѓв”Ѓв”Ѓв”Ѓв”Ѓв”Ѓв”Ѓв”Ѓ\u001b[0m \u001b[1m2s\u001b[0m 186ms/step - accuracy: 0.7035 - loss: 1.5925"
        },
        {
          "type": "stream",
          "name": "stdout",
          "text": "\b\b\b\b\b\b\b\b\b\b\b\b\b\b\b\b\b\b\b\b\b\b\b\b\b\b\b\b\b\b\b\b\b\b\b\b\b\b\b\b\b\b\b\b\b\b\b\b\b\b\b\b\b\b\b\b\b\b\b\b\b\b\b\b\b\b\b\b\b\b\b\b\b\b\r\u001b[1m23/34\u001b[0m \u001b[32mв”Ѓв”Ѓв”Ѓв”Ѓв”Ѓв”Ѓв”Ѓв”Ѓв”Ѓв”Ѓв”Ѓв”Ѓв”Ѓ\u001b[0m\u001b[37mв”Ѓв”Ѓв”Ѓв”Ѓв”Ѓв”Ѓв”Ѓ\u001b[0m \u001b[1m2s\u001b[0m 185ms/step - accuracy: 0.7037 - loss: 1.5912"
        },
        {
          "type": "stream",
          "name": "stdout",
          "text": "\b\b\b\b\b\b\b\b\b\b\b\b\b\b\b\b\b\b\b\b\b\b\b\b\b\b\b\b\b\b\b\b\b\b\b\b\b\b\b\b\b\b\b\b\b\b\b\b\b\b\b\b\b\b\b\b\b\b\b\b\b\b\b\b\b\b\b\b\b\b\b\b\b\b\r\u001b[1m24/34\u001b[0m \u001b[32mв”Ѓв”Ѓв”Ѓв”Ѓв”Ѓв”Ѓв”Ѓв”Ѓв”Ѓв”Ѓв”Ѓв”Ѓв”Ѓв”Ѓ\u001b[0m\u001b[37mв”Ѓв”Ѓв”Ѓв”Ѓв”Ѓв”Ѓ\u001b[0m \u001b[1m1s\u001b[0m 185ms/step - accuracy: 0.7039 - loss: 1.5902"
        },
        {
          "type": "stream",
          "name": "stdout",
          "text": "\b\b\b\b\b\b\b\b\b\b\b\b\b\b\b\b\b\b\b\b\b\b\b\b\b\b\b\b\b\b\b\b\b\b\b\b\b\b\b\b\b\b\b\b\b\b\b\b\b\b\b\b\b\b\b\b\b\b\b\b\b\b\b\b\b\b\b\b\b\b\b\b\b\b\r\u001b[1m25/34\u001b[0m \u001b[32mв”Ѓв”Ѓв”Ѓв”Ѓв”Ѓв”Ѓв”Ѓв”Ѓв”Ѓв”Ѓв”Ѓв”Ѓв”Ѓв”Ѓ\u001b[0m\u001b[37mв”Ѓв”Ѓв”Ѓв”Ѓв”Ѓв”Ѓ\u001b[0m \u001b[1m1s\u001b[0m 183ms/step - accuracy: 0.7040 - loss: 1.5892"
        },
        {
          "type": "stream",
          "name": "stdout",
          "text": "\b\b\b\b\b\b\b\b\b\b\b\b\b\b\b\b\b\b\b\b\b\b\b\b\b\b\b\b\b\b\b\b\b\b\b\b\b\b\b\b\b\b\b\b\b\b\b\b\b\b\b\b\b\b\b\b\b\b\b\b\b\b\b\b\b\b\b\b\b\b\b\b\b\b\r\u001b[1m26/34\u001b[0m \u001b[32mв”Ѓв”Ѓв”Ѓв”Ѓв”Ѓв”Ѓв”Ѓв”Ѓв”Ѓв”Ѓв”Ѓв”Ѓв”Ѓв”Ѓв”Ѓ\u001b[0m\u001b[37mв”Ѓв”Ѓв”Ѓв”Ѓв”Ѓ\u001b[0m \u001b[1m1s\u001b[0m 183ms/step - accuracy: 0.7042 - loss: 1.5882"
        },
        {
          "type": "stream",
          "name": "stdout",
          "text": "\b\b\b\b\b\b\b\b\b\b\b\b\b\b\b\b\b\b\b\b\b\b\b\b\b\b\b\b\b\b\b\b\b\b\b\b\b\b\b\b\b\b\b\b\b\b\b\b\b\b\b\b\b\b\b\b\b\b\b\b\b\b\b\b\b\b\b\b\b\b\b\b\b\b\r\u001b[1m27/34\u001b[0m \u001b[32mв”Ѓв”Ѓв”Ѓв”Ѓв”Ѓв”Ѓв”Ѓв”Ѓв”Ѓв”Ѓв”Ѓв”Ѓв”Ѓв”Ѓв”Ѓ\u001b[0m\u001b[37mв”Ѓв”Ѓв”Ѓв”Ѓв”Ѓ\u001b[0m \u001b[1m1s\u001b[0m 183ms/step - accuracy: 0.7042 - loss: 1.5877"
        },
        {
          "type": "stream",
          "name": "stdout",
          "text": "\b\b\b\b\b\b\b\b\b\b\b\b\b\b\b\b\b\b\b\b\b\b\b\b\b\b\b\b\b\b\b\b\b\b\b\b\b\b\b\b\b\b\b\b\b\b\b\b\b\b\b\b\b\b\b\b\b\b\b\b\b\b\b\b\b\b\b\b\b\b\b\b\b\b\r\u001b[1m28/34\u001b[0m \u001b[32mв”Ѓв”Ѓв”Ѓв”Ѓв”Ѓв”Ѓв”Ѓв”Ѓв”Ѓв”Ѓв”Ѓв”Ѓв”Ѓв”Ѓв”Ѓв”Ѓ\u001b[0m\u001b[37mв”Ѓв”Ѓв”Ѓв”Ѓ\u001b[0m \u001b[1m1s\u001b[0m 181ms/step - accuracy: 0.7042 - loss: 1.5871"
        },
        {
          "type": "stream",
          "name": "stdout",
          "text": "\b\b\b\b\b\b\b\b\b\b\b\b\b\b\b\b\b\b\b\b\b\b\b\b\b\b\b\b\b\b\b\b\b\b\b\b\b\b\b\b\b\b\b\b\b\b\b\b\b\b\b\b\b\b\b\b\b\b\b\b\b\b\b\b\b\b\b\b\b\b\b\b\b\b\r\u001b[1m29/34\u001b[0m \u001b[32mв”Ѓв”Ѓв”Ѓв”Ѓв”Ѓв”Ѓв”Ѓв”Ѓв”Ѓв”Ѓв”Ѓв”Ѓв”Ѓв”Ѓв”Ѓв”Ѓв”Ѓ\u001b[0m\u001b[37mв”Ѓв”Ѓв”Ѓ\u001b[0m \u001b[1m0s\u001b[0m 178ms/step - accuracy: 0.7042 - loss: 1.5866"
        },
        {
          "type": "stream",
          "name": "stdout",
          "text": "\b\b\b\b\b\b\b\b\b\b\b\b\b\b\b\b\b\b\b\b\b\b\b\b\b\b\b\b\b\b\b\b\b\b\b\b\b\b\b\b\b\b\b\b\b\b\b\b\b\b\b\b\b\b\b\b\b\b\b\b\b\b\b\b\b\b\b\b\b\b\b\b\b\b\r\u001b[1m30/34\u001b[0m \u001b[32mв”Ѓв”Ѓв”Ѓв”Ѓв”Ѓв”Ѓв”Ѓв”Ѓв”Ѓв”Ѓв”Ѓв”Ѓв”Ѓв”Ѓв”Ѓв”Ѓв”Ѓ\u001b[0m\u001b[37mв”Ѓв”Ѓв”Ѓ\u001b[0m \u001b[1m0s\u001b[0m 176ms/step - accuracy: 0.7043 - loss: 1.5859"
        },
        {
          "type": "stream",
          "name": "stdout",
          "text": "\b\b\b\b\b\b\b\b\b\b\b\b\b\b\b\b\b\b\b\b\b\b\b\b\b\b\b\b\b\b\b\b\b\b\b\b\b\b\b\b\b\b\b\b\b\b\b\b\b\b\b\b\b\b\b\b\b\b\b\b\b\b\b\b\b\b\b\b\b\b\b\b\b\b\r\u001b[1m31/34\u001b[0m \u001b[32mв”Ѓв”Ѓв”Ѓв”Ѓв”Ѓв”Ѓв”Ѓв”Ѓв”Ѓв”Ѓв”Ѓв”Ѓв”Ѓв”Ѓв”Ѓв”Ѓв”Ѓв”Ѓ\u001b[0m\u001b[37mв”Ѓв”Ѓ\u001b[0m \u001b[1m0s\u001b[0m 174ms/step - accuracy: 0.7043 - loss: 1.5851"
        },
        {
          "type": "stream",
          "name": "stdout",
          "text": "\b\b\b\b\b\b\b\b\b\b\b\b\b\b\b\b\b\b\b\b\b\b\b\b\b\b\b\b\b\b\b\b\b\b\b\b\b\b\b\b\b\b\b\b\b\b\b\b\b\b\b\b\b\b\b\b\b\b\b\b\b\b\b\b\b\b\b\b\b\b\b\b\b\b\r\u001b[1m32/34\u001b[0m \u001b[32mв”Ѓв”Ѓв”Ѓв”Ѓв”Ѓв”Ѓв”Ѓв”Ѓв”Ѓв”Ѓв”Ѓв”Ѓв”Ѓв”Ѓв”Ѓв”Ѓв”Ѓв”Ѓ\u001b[0m\u001b[37mв”Ѓв”Ѓ\u001b[0m \u001b[1m0s\u001b[0m 171ms/step - accuracy: 0.7044 - loss: 1.5841"
        },
        {
          "type": "stream",
          "name": "stdout",
          "text": "\b\b\b\b\b\b\b\b\b\b\b\b\b\b\b\b\b\b\b\b\b\b\b\b\b\b\b\b\b\b\b\b\b\b\b\b\b\b\b\b\b\b\b\b\b\b\b\b\b\b\b\b\b\b\b\b\b\b\b\b\b\b\b\b\b\b\b\b\b\b\b\b\b\b\r\u001b[1m33/34\u001b[0m \u001b[32mв”Ѓв”Ѓв”Ѓв”Ѓв”Ѓв”Ѓв”Ѓв”Ѓв”Ѓв”Ѓв”Ѓв”Ѓв”Ѓв”Ѓв”Ѓв”Ѓв”Ѓв”Ѓв”Ѓ\u001b[0m\u001b[37mв”Ѓ\u001b[0m \u001b[1m0s\u001b[0m 169ms/step - accuracy: 0.7045 - loss: 1.5831"
        },
        {
          "type": "stream",
          "name": "stdout",
          "text": "\b\b\b\b\b\b\b\b\b\b\b\b\b\b\b\b\b\b\b\b\b\b\b\b\b\b\b\b\b\b\b\b\b\b\b\b\b\b\b\b\b\b\b\b\b\b\b\b\b\b\b\b\b\b\b\b\b\b\b\b\b\b\b\b\b\b\b\b\b\b\b\b\b\b\r\u001b[1m34/34\u001b[0m \u001b[32mв”Ѓв”Ѓв”Ѓв”Ѓв”Ѓв”Ѓв”Ѓв”Ѓв”Ѓв”Ѓв”Ѓв”Ѓв”Ѓв”Ѓв”Ѓв”Ѓв”Ѓв”Ѓв”Ѓв”Ѓ\u001b[0m\u001b[37m\u001b[0m \u001b[1m0s\u001b[0m 167ms/step - accuracy: 0.7046 - loss: 1.5822"
        },
        {
          "type": "stream",
          "name": "stdout",
          "text": "\b\b\b\b\b\b\b\b\b\b\b\b\b\b\b\b\b\b\b\b\b\b\b\b\b\b\b\b\b\b\b\b\b\b\b\b\b\b\b\b\b\b\b\b\b\b\b\b\b\b\b\b\b\b\b\b\b\b\b\b\b\b\b\b\b\b\b\b\b\b\b\b\b\b\r\u001b[1m34/34\u001b[0m \u001b[32mв”Ѓв”Ѓв”Ѓв”Ѓв”Ѓв”Ѓв”Ѓв”Ѓв”Ѓв”Ѓв”Ѓв”Ѓв”Ѓв”Ѓв”Ѓв”Ѓв”Ѓв”Ѓв”Ѓв”Ѓ\u001b[0m\u001b[37m\u001b[0m \u001b[1m10s\u001b[0m 299ms/step - accuracy: 0.7072 - loss: 1.5531 - val_accuracy: 0.7287 - val_loss: 1.9787\n"
        },
        {
          "type": "stream",
          "name": "stdout",
          "text": "Epoch 3/5\n"
        },
        {
          "type": "stream",
          "name": "stdout",
          "text": "\r\u001b[1m 1/34\u001b[0m \u001b[37mв”Ѓв”Ѓв”Ѓв”Ѓв”Ѓв”Ѓв”Ѓв”Ѓв”Ѓв”Ѓв”Ѓв”Ѓв”Ѓв”Ѓв”Ѓв”Ѓв”Ѓв”Ѓв”Ѓв”Ѓ\u001b[0m \u001b[1m8s\u001b[0m 269ms/step - accuracy: 0.7145 - loss: 1.5180"
        },
        {
          "type": "stream",
          "name": "stdout",
          "text": "\b\b\b\b\b\b\b\b\b\b\b\b\b\b\b\b\b\b\b\b\b\b\b\b\b\b\b\b\b\b\b\b\b\b\b\b\b\b\b\b\b\b\b\b\b\b\b\b\b\b\b\b\b\b\b\b\b\b\b\b\b\b\b\b\b\b\b\b\b\b\b\b\b\b\r\u001b[1m 2/34\u001b[0m \u001b[32mв”Ѓ\u001b[0m\u001b[37mв”Ѓв”Ѓв”Ѓв”Ѓв”Ѓв”Ѓв”Ѓв”Ѓв”Ѓв”Ѓв”Ѓв”Ѓв”Ѓв”Ѓв”Ѓв”Ѓв”Ѓв”Ѓв”Ѓ\u001b[0m \u001b[1m15s\u001b[0m 490ms/step - accuracy: 0.7238 - loss: 1.4768"
        },
        {
          "type": "stream",
          "name": "stdout",
          "text": "\b\b\b\b\b\b\b\b\b\b\b\b\b\b\b\b\b\b\b\b\b\b\b\b\b\b\b\b\b\b\b\b\b\b\b\b\b\b\b\b\b\b\b\b\b\b\b\b\b\b\b\b\b\b\b\b\b\b\b\b\b\b\b\b\b\b\b\b\b\b\b\b\b\b\b\r\u001b[1m 3/34\u001b[0m \u001b[32mв”Ѓ\u001b[0m\u001b[37mв”Ѓв”Ѓв”Ѓв”Ѓв”Ѓв”Ѓв”Ѓв”Ѓв”Ѓв”Ѓв”Ѓв”Ѓв”Ѓв”Ѓв”Ѓв”Ѓв”Ѓв”Ѓв”Ѓ\u001b[0m \u001b[1m11s\u001b[0m 364ms/step - accuracy: 0.7180 - loss: 1.4948"
        },
        {
          "type": "stream",
          "name": "stdout",
          "text": "\b\b\b\b\b\b\b\b\b\b\b\b\b\b\b\b\b\b\b\b\b\b\b\b\b\b\b\b\b\b\b\b\b\b\b\b\b\b\b\b\b\b\b\b\b\b\b\b\b\b\b\b\b\b\b\b\b\b\b\b\b\b\b\b\b\b\b\b\b\b\b\b\b\b\b\r\u001b[1m 4/34\u001b[0m \u001b[32mв”Ѓв”Ѓ\u001b[0m\u001b[37mв”Ѓв”Ѓв”Ѓв”Ѓв”Ѓв”Ѓв”Ѓв”Ѓв”Ѓв”Ѓв”Ѓв”Ѓв”Ѓв”Ѓв”Ѓв”Ѓв”Ѓв”Ѓ\u001b[0m \u001b[1m10s\u001b[0m 357ms/step - accuracy: 0.7160 - loss: 1.4957"
        },
        {
          "type": "stream",
          "name": "stdout",
          "text": "\b\b\b\b\b\b\b\b\b\b\b\b\b\b\b\b\b\b\b\b\b\b\b\b\b\b\b\b\b\b\b\b\b\b\b\b\b\b\b\b\b\b\b\b\b\b\b\b\b\b\b\b\b\b\b\b\b\b\b\b\b\b\b\b\b\b\b\b\b\b\b\b\b\b\b\r\u001b[1m 5/34\u001b[0m \u001b[32mв”Ѓв”Ѓ\u001b[0m\u001b[37mв”Ѓв”Ѓв”Ѓв”Ѓв”Ѓв”Ѓв”Ѓв”Ѓв”Ѓв”Ѓв”Ѓв”Ѓв”Ѓв”Ѓв”Ѓв”Ѓв”Ѓв”Ѓ\u001b[0m \u001b[1m9s\u001b[0m 310ms/step - accuracy: 0.7145 - loss: 1.4976 "
        },
        {
          "type": "stream",
          "name": "stdout",
          "text": "\b\b\b\b\b\b\b\b\b\b\b\b\b\b\b\b\b\b\b\b\b\b\b\b\b\b\b\b\b\b\b\b\b\b\b\b\b\b\b\b\b\b\b\b\b\b\b\b\b\b\b\b\b\b\b\b\b\b\b\b\b\b\b\b\b\b\b\b\b\b\b\b\b\b\r\u001b[1m 6/34\u001b[0m \u001b[32mв”Ѓв”Ѓв”Ѓ\u001b[0m\u001b[37mв”Ѓв”Ѓв”Ѓв”Ѓв”Ѓв”Ѓв”Ѓв”Ѓв”Ѓв”Ѓв”Ѓв”Ѓв”Ѓв”Ѓв”Ѓв”Ѓв”Ѓ\u001b[0m \u001b[1m7s\u001b[0m 282ms/step - accuracy: 0.7127 - loss: 1.5030"
        },
        {
          "type": "stream",
          "name": "stdout",
          "text": "\b\b\b\b\b\b\b\b\b\b\b\b\b\b\b\b\b\b\b\b\b\b\b\b\b\b\b\b\b\b\b\b\b\b\b\b\b\b\b\b\b\b\b\b\b\b\b\b\b\b\b\b\b\b\b\b\b\b\b\b\b\b\b\b\b\b\b\b\b\b\b\b\b\b\r\u001b[1m 7/34\u001b[0m \u001b[32mв”Ѓв”Ѓв”Ѓв”Ѓ\u001b[0m\u001b[37mв”Ѓв”Ѓв”Ѓв”Ѓв”Ѓв”Ѓв”Ѓв”Ѓв”Ѓв”Ѓв”Ѓв”Ѓв”Ѓв”Ѓв”Ѓв”Ѓ\u001b[0m \u001b[1m7s\u001b[0m 276ms/step - accuracy: 0.7123 - loss: 1.5021"
        },
        {
          "type": "stream",
          "name": "stdout",
          "text": "\b\b\b\b\b\b\b\b\b\b\b\b\b\b\b\b\b\b\b\b\b\b\b\b\b\b\b\b\b\b\b\b\b\b\b\b\b\b\b\b\b\b\b\b\b\b\b\b\b\b\b\b\b\b\b\b\b\b\b\b\b\b\b\b\b\b\b\b\b\b\b\b\b\b\r\u001b[1m 8/34\u001b[0m \u001b[32mв”Ѓв”Ѓв”Ѓв”Ѓ\u001b[0m\u001b[37mв”Ѓв”Ѓв”Ѓв”Ѓв”Ѓв”Ѓв”Ѓв”Ѓв”Ѓв”Ѓв”Ѓв”Ѓв”Ѓв”Ѓв”Ѓв”Ѓ\u001b[0m \u001b[1m6s\u001b[0m 265ms/step - accuracy: 0.7123 - loss: 1.5000"
        },
        {
          "type": "stream",
          "name": "stdout",
          "text": "\b\b\b\b\b\b\b\b\b\b\b\b\b\b\b\b\b\b\b\b\b\b\b\b\b\b\b\b\b\b\b\b\b\b\b\b\b\b\b\b\b\b\b\b\b\b\b\b\b\b\b\b\b\b\b\b\b\b\b\b\b\b\b\b\b\b\b\b\b\b\b\b\b\b\r\u001b[1m 9/34\u001b[0m \u001b[32mв”Ѓв”Ѓв”Ѓв”Ѓв”Ѓ\u001b[0m\u001b[37mв”Ѓв”Ѓв”Ѓв”Ѓв”Ѓв”Ѓв”Ѓв”Ѓв”Ѓв”Ѓв”Ѓв”Ѓв”Ѓв”Ѓв”Ѓ\u001b[0m \u001b[1m6s\u001b[0m 251ms/step - accuracy: 0.7124 - loss: 1.4977"
        },
        {
          "type": "stream",
          "name": "stdout",
          "text": "\b\b\b\b\b\b\b\b\b\b\b\b\b\b\b\b\b\b\b\b\b\b\b\b\b\b\b\b\b\b\b\b\b\b\b\b\b\b\b\b\b\b\b\b\b\b\b\b\b\b\b\b\b\b\b\b\b\b\b\b\b\b\b\b\b\b\b\b\b\b\b\b\b\b\r\u001b[1m10/34\u001b[0m \u001b[32mв”Ѓв”Ѓв”Ѓв”Ѓв”Ѓ\u001b[0m\u001b[37mв”Ѓв”Ѓв”Ѓв”Ѓв”Ѓв”Ѓв”Ѓв”Ѓв”Ѓв”Ѓв”Ѓв”Ѓв”Ѓв”Ѓв”Ѓ\u001b[0m \u001b[1m5s\u001b[0m 243ms/step - accuracy: 0.7130 - loss: 1.4942"
        },
        {
          "type": "stream",
          "name": "stdout",
          "text": "\b\b\b\b\b\b\b\b\b\b\b\b\b\b\b\b\b\b\b\b\b\b\b\b\b\b\b\b\b\b\b\b\b\b\b\b\b\b\b\b\b\b\b\b\b\b\b\b\b\b\b\b\b\b\b\b\b\b\b\b\b\b\b\b\b\b\b\b\b\b\b\b\b\b\r\u001b[1m11/34\u001b[0m \u001b[32mв”Ѓв”Ѓв”Ѓв”Ѓв”Ѓв”Ѓ\u001b[0m\u001b[37mв”Ѓв”Ѓв”Ѓв”Ѓв”Ѓв”Ѓв”Ѓв”Ѓв”Ѓв”Ѓв”Ѓв”Ѓв”Ѓв”Ѓ\u001b[0m \u001b[1m5s\u001b[0m 240ms/step - accuracy: 0.7124 - loss: 1.4958"
        },
        {
          "type": "stream",
          "name": "stdout",
          "text": "\b\b\b\b\b\b\b\b\b\b\b\b\b\b\b\b\b\b\b\b\b\b\b\b\b\b\b\b\b\b\b\b\b\b\b\b\b\b\b\b\b\b\b\b\b\b\b\b\b\b\b\b\b\b\b\b\b\b\b\b\b\b\b\b\b\b\b\b\b\b\b\b\b\b\r\u001b[1m12/34\u001b[0m \u001b[32mв”Ѓв”Ѓв”Ѓв”Ѓв”Ѓв”Ѓв”Ѓ\u001b[0m\u001b[37mв”Ѓв”Ѓв”Ѓв”Ѓв”Ѓв”Ѓв”Ѓв”Ѓв”Ѓв”Ѓв”Ѓв”Ѓв”Ѓ\u001b[0m \u001b[1m5s\u001b[0m 235ms/step - accuracy: 0.7119 - loss: 1.4965"
        },
        {
          "type": "stream",
          "name": "stdout",
          "text": "\b\b\b\b\b\b\b\b\b\b\b\b\b\b\b\b\b\b\b\b\b\b\b\b\b\b\b\b\b\b\b\b\b\b\b\b\b\b\b\b\b\b\b\b\b\b\b\b\b\b\b\b\b\b\b\b\b\b\b\b\b\b\b\b\b\b\b\b\b\b\b\b\b\b\r\u001b[1m13/34\u001b[0m \u001b[32mв”Ѓв”Ѓв”Ѓв”Ѓв”Ѓв”Ѓв”Ѓ\u001b[0m\u001b[37mв”Ѓв”Ѓв”Ѓв”Ѓв”Ѓв”Ѓв”Ѓв”Ѓв”Ѓв”Ѓв”Ѓв”Ѓв”Ѓ\u001b[0m \u001b[1m4s\u001b[0m 228ms/step - accuracy: 0.7115 - loss: 1.4980"
        },
        {
          "type": "stream",
          "name": "stdout",
          "text": "\b\b\b\b\b\b\b\b\b\b\b\b\b\b\b\b\b\b\b\b\b\b\b\b\b\b\b\b\b\b\b\b\b\b\b\b\b\b\b\b\b\b\b\b\b\b\b\b\b\b\b\b\b\b\b\b\b\b\b\b\b\b\b\b\b\b\b\b\b\b\b\b\b\b\r\u001b[1m14/34\u001b[0m \u001b[32mв”Ѓв”Ѓв”Ѓв”Ѓв”Ѓв”Ѓв”Ѓв”Ѓ\u001b[0m\u001b[37mв”Ѓв”Ѓв”Ѓв”Ѓв”Ѓв”Ѓв”Ѓв”Ѓв”Ѓв”Ѓв”Ѓв”Ѓ\u001b[0m \u001b[1m4s\u001b[0m 222ms/step - accuracy: 0.7112 - loss: 1.4990"
        },
        {
          "type": "stream",
          "name": "stdout",
          "text": "\b\b\b\b\b\b\b\b\b\b\b\b\b\b\b\b\b\b\b\b\b\b\b\b\b\b\b\b\b\b\b\b\b\b\b\b\b\b\b\b\b\b\b\b\b\b\b\b\b\b\b\b\b\b\b\b\b\b\b\b\b\b\b\b\b\b\b\b\b\b\b\b\b\b\r\u001b[1m15/34\u001b[0m \u001b[32mв”Ѓв”Ѓв”Ѓв”Ѓв”Ѓв”Ѓв”Ѓв”Ѓ\u001b[0m\u001b[37mв”Ѓв”Ѓв”Ѓв”Ѓв”Ѓв”Ѓв”Ѓв”Ѓв”Ѓв”Ѓв”Ѓв”Ѓ\u001b[0m \u001b[1m4s\u001b[0m 218ms/step - accuracy: 0.7109 - loss: 1.4997"
        },
        {
          "type": "stream",
          "name": "stdout",
          "text": "\b\b\b\b\b\b\b\b\b\b\b\b\b\b\b\b\b\b\b\b\b\b\b\b\b\b\b\b\b\b\b\b\b\b\b\b\b\b\b\b\b\b\b\b\b\b\b\b\b\b\b\b\b\b\b\b\b\b\b\b\b\b\b\b\b\b\b\b\b\b\b\b\b\b\r\u001b[1m16/34\u001b[0m \u001b[32mв”Ѓв”Ѓв”Ѓв”Ѓв”Ѓв”Ѓв”Ѓв”Ѓв”Ѓ\u001b[0m\u001b[37mв”Ѓв”Ѓв”Ѓв”Ѓв”Ѓв”Ѓв”Ѓв”Ѓв”Ѓв”Ѓв”Ѓ\u001b[0m \u001b[1m3s\u001b[0m 213ms/step - accuracy: 0.7108 - loss: 1.4999"
        },
        {
          "type": "stream",
          "name": "stdout",
          "text": "\b\b\b\b\b\b\b\b\b\b\b\b\b\b\b\b\b\b\b\b\b\b\b\b\b\b\b\b\b\b\b\b\b\b\b\b\b\b\b\b\b\b\b\b\b\b\b\b\b\b\b\b\b\b\b\b\b\b\b\b\b\b\b\b\b\b\b\b\b\b\b\b\b\b\r\u001b[1m17/34\u001b[0m \u001b[32mв”Ѓв”Ѓв”Ѓв”Ѓв”Ѓв”Ѓв”Ѓв”Ѓв”Ѓв”Ѓ\u001b[0m\u001b[37mв”Ѓв”Ѓв”Ѓв”Ѓв”Ѓв”Ѓв”Ѓв”Ѓв”Ѓв”Ѓ\u001b[0m \u001b[1m3s\u001b[0m 210ms/step - accuracy: 0.7109 - loss: 1.4996"
        },
        {
          "type": "stream",
          "name": "stdout",
          "text": "\b\b\b\b\b\b\b\b\b\b\b\b\b\b\b\b\b\b\b\b\b\b\b\b\b\b\b\b\b\b\b\b\b\b\b\b\b\b\b\b\b\b\b\b\b\b\b\b\b\b\b\b\b\b\b\b\b\b\b\b\b\b\b\b\b\b\b\b\b\b\b\b\b\b\r\u001b[1m18/34\u001b[0m \u001b[32mв”Ѓв”Ѓв”Ѓв”Ѓв”Ѓв”Ѓв”Ѓв”Ѓв”Ѓв”Ѓ\u001b[0m\u001b[37mв”Ѓв”Ѓв”Ѓв”Ѓв”Ѓв”Ѓв”Ѓв”Ѓв”Ѓв”Ѓ\u001b[0m \u001b[1m3s\u001b[0m 207ms/step - accuracy: 0.7111 - loss: 1.4990"
        },
        {
          "type": "stream",
          "name": "stdout",
          "text": "\b\b\b\b\b\b\b\b\b\b\b\b\b\b\b\b\b\b\b\b\b\b\b\b\b\b\b\b\b\b\b\b\b\b\b\b\b\b\b\b\b\b\b\b\b\b\b\b\b\b\b\b\b\b\b\b\b\b\b\b\b\b\b\b\b\b\b\b\b\b\b\b\b\b\r\u001b[1m19/34\u001b[0m \u001b[32mв”Ѓв”Ѓв”Ѓв”Ѓв”Ѓв”Ѓв”Ѓв”Ѓв”Ѓв”Ѓв”Ѓ\u001b[0m\u001b[37mв”Ѓв”Ѓв”Ѓв”Ѓв”Ѓв”Ѓв”Ѓв”Ѓв”Ѓ\u001b[0m \u001b[1m3s\u001b[0m 203ms/step - accuracy: 0.7114 - loss: 1.4978"
        },
        {
          "type": "stream",
          "name": "stdout",
          "text": "\b\b\b\b\b\b\b\b\b\b\b\b\b\b\b\b\b\b\b\b\b\b\b\b\b\b\b\b\b\b\b\b\b\b\b\b\b\b\b\b\b\b\b\b\b\b\b\b\b\b\b\b\b\b\b\b\b\b\b\b\b\b\b\b\b\b\b\b\b\b\b\b\b\b\r\u001b[1m20/34\u001b[0m \u001b[32mв”Ѓв”Ѓв”Ѓв”Ѓв”Ѓв”Ѓв”Ѓв”Ѓв”Ѓв”Ѓв”Ѓ\u001b[0m\u001b[37mв”Ѓв”Ѓв”Ѓв”Ѓв”Ѓв”Ѓв”Ѓв”Ѓв”Ѓ\u001b[0m \u001b[1m2s\u001b[0m 200ms/step - accuracy: 0.7115 - loss: 1.4970"
        },
        {
          "type": "stream",
          "name": "stdout",
          "text": "\b\b\b\b\b\b\b\b\b\b\b\b\b\b\b\b\b\b\b\b\b\b\b\b\b\b\b\b\b\b\b\b\b\b\b\b\b\b\b\b\b\b\b\b\b\b\b\b\b\b\b\b\b\b\b\b\b\b\b\b\b\b\b\b\b\b\b\b\b\b\b\b\b\b\r\u001b[1m21/34\u001b[0m \u001b[32mв”Ѓв”Ѓв”Ѓв”Ѓв”Ѓв”Ѓв”Ѓв”Ѓв”Ѓв”Ѓв”Ѓв”Ѓ\u001b[0m\u001b[37mв”Ѓв”Ѓв”Ѓв”Ѓв”Ѓв”Ѓв”Ѓв”Ѓ\u001b[0m \u001b[1m2s\u001b[0m 196ms/step - accuracy: 0.7116 - loss: 1.4970"
        },
        {
          "type": "stream",
          "name": "stdout",
          "text": "\b\b\b\b\b\b\b\b\b\b\b\b\b\b\b\b\b\b\b\b\b\b\b\b\b\b\b\b\b\b\b\b\b\b\b\b\b\b\b\b\b\b\b\b\b\b\b\b\b\b\b\b\b\b\b\b\b\b\b\b\b\b\b\b\b\b\b\b\b\b\b\b\b\b\r\u001b[1m22/34\u001b[0m \u001b[32mв”Ѓв”Ѓв”Ѓв”Ѓв”Ѓв”Ѓв”Ѓв”Ѓв”Ѓв”Ѓв”Ѓв”Ѓ\u001b[0m\u001b[37mв”Ѓв”Ѓв”Ѓв”Ѓв”Ѓв”Ѓв”Ѓв”Ѓ\u001b[0m \u001b[1m2s\u001b[0m 195ms/step - accuracy: 0.7117 - loss: 1.4966"
        },
        {
          "type": "stream",
          "name": "stdout",
          "text": "\b\b\b\b\b\b\b\b\b\b\b\b\b\b\b\b\b\b\b\b\b\b\b\b\b\b\b\b\b\b\b\b\b\b\b\b\b\b\b\b\b\b\b\b\b\b\b\b\b\b\b\b\b\b\b\b\b\b\b\b\b\b\b\b\b\b\b\b\b\b\b\b\b\b\r\u001b[1m23/34\u001b[0m \u001b[32mв”Ѓв”Ѓв”Ѓв”Ѓв”Ѓв”Ѓв”Ѓв”Ѓв”Ѓв”Ѓв”Ѓв”Ѓв”Ѓ\u001b[0m\u001b[37mв”Ѓв”Ѓв”Ѓв”Ѓв”Ѓв”Ѓв”Ѓ\u001b[0m \u001b[1m2s\u001b[0m 194ms/step - accuracy: 0.7119 - loss: 1.4959"
        },
        {
          "type": "stream",
          "name": "stdout",
          "text": "\b\b\b\b\b\b\b\b\b\b\b\b\b\b\b\b\b\b\b\b\b\b\b\b\b\b\b\b\b\b\b\b\b\b\b\b\b\b\b\b\b\b\b\b\b\b\b\b\b\b\b\b\b\b\b\b\b\b\b\b\b\b\b\b\b\b\b\b\b\b\b\b\b\b\r\u001b[1m24/34\u001b[0m \u001b[32mв”Ѓв”Ѓв”Ѓв”Ѓв”Ѓв”Ѓв”Ѓв”Ѓв”Ѓв”Ѓв”Ѓв”Ѓв”Ѓв”Ѓ\u001b[0m\u001b[37mв”Ѓв”Ѓв”Ѓв”Ѓв”Ѓв”Ѓ\u001b[0m \u001b[1m1s\u001b[0m 193ms/step - accuracy: 0.7120 - loss: 1.4953"
        },
        {
          "type": "stream",
          "name": "stdout",
          "text": "\b\b\b\b\b\b\b\b\b\b\b\b\b\b\b\b\b\b\b\b\b\b\b\b\b\b\b\b\b\b\b\b\b\b\b\b\b\b\b\b\b\b\b\b\b\b\b\b\b\b\b\b\b\b\b\b\b\b\b\b\b\b\b\b\b\b\b\b\b\b\b\b\b\b\r\u001b[1m25/34\u001b[0m \u001b[32mв”Ѓв”Ѓв”Ѓв”Ѓв”Ѓв”Ѓв”Ѓв”Ѓв”Ѓв”Ѓв”Ѓв”Ѓв”Ѓв”Ѓ\u001b[0m\u001b[37mв”Ѓв”Ѓв”Ѓв”Ѓв”Ѓв”Ѓ\u001b[0m \u001b[1m1s\u001b[0m 192ms/step - accuracy: 0.7120 - loss: 1.4950"
        },
        {
          "type": "stream",
          "name": "stdout",
          "text": "\b\b\b\b\b\b\b\b\b\b\b\b\b\b\b\b\b\b\b\b\b\b\b\b\b\b\b\b\b\b\b\b\b\b\b\b\b\b\b\b\b\b\b\b\b\b\b\b\b\b\b\b\b\b\b\b\b\b\b\b\b\b\b\b\b\b\b\b\b\b\b\b\b\b\r\u001b[1m26/34\u001b[0m \u001b[32mв”Ѓв”Ѓв”Ѓв”Ѓв”Ѓв”Ѓв”Ѓв”Ѓв”Ѓв”Ѓв”Ѓв”Ѓв”Ѓв”Ѓв”Ѓ\u001b[0m\u001b[37mв”Ѓв”Ѓв”Ѓв”Ѓв”Ѓ\u001b[0m \u001b[1m1s\u001b[0m 195ms/step - accuracy: 0.7120 - loss: 1.4948"
        },
        {
          "type": "stream",
          "name": "stdout",
          "text": "\b\b\b\b\b\b\b\b\b\b\b\b\b\b\b\b\b\b\b\b\b\b\b\b\b\b\b\b\b\b\b\b\b\b\b\b\b\b\b\b\b\b\b\b\b\b\b\b\b\b\b\b\b\b\b\b\b\b\b\b\b\b\b\b\b\b\b\b\b\b\b\b\b\b\r\u001b[1m27/34\u001b[0m \u001b[32mв”Ѓв”Ѓв”Ѓв”Ѓв”Ѓв”Ѓв”Ѓв”Ѓв”Ѓв”Ѓв”Ѓв”Ѓв”Ѓв”Ѓв”Ѓ\u001b[0m\u001b[37mв”Ѓв”Ѓв”Ѓв”Ѓв”Ѓ\u001b[0m \u001b[1m1s\u001b[0m 193ms/step - accuracy: 0.7121 - loss: 1.4944"
        },
        {
          "type": "stream",
          "name": "stdout",
          "text": "\b\b\b\b\b\b\b\b\b\b\b\b\b\b\b\b\b\b\b\b\b\b\b\b\b\b\b\b\b\b\b\b\b\b\b\b\b\b\b\b\b\b\b\b\b\b\b\b\b\b\b\b\b\b\b\b\b\b\b\b\b\b\b\b\b\b\b\b\b\b\b\b\b\b\r\u001b[1m28/34\u001b[0m \u001b[32mв”Ѓв”Ѓв”Ѓв”Ѓв”Ѓв”Ѓв”Ѓв”Ѓв”Ѓв”Ѓв”Ѓв”Ѓв”Ѓв”Ѓв”Ѓв”Ѓ\u001b[0m\u001b[37mв”Ѓв”Ѓв”Ѓв”Ѓ\u001b[0m \u001b[1m1s\u001b[0m 189ms/step - accuracy: 0.7121 - loss: 1.4940"
        },
        {
          "type": "stream",
          "name": "stdout",
          "text": "\b\b\b\b\b\b\b\b\b\b\b\b\b\b\b\b\b\b\b\b\b\b\b\b\b\b\b\b\b\b\b\b\b\b\b\b\b\b\b\b\b\b\b\b\b\b\b\b\b\b\b\b\b\b\b\b\b\b\b\b\b\b\b\b\b\b\b\b\b\b\b\b\b\b\r\u001b[1m29/34\u001b[0m \u001b[32mв”Ѓв”Ѓв”Ѓв”Ѓв”Ѓв”Ѓв”Ѓв”Ѓв”Ѓв”Ѓв”Ѓв”Ѓв”Ѓв”Ѓв”Ѓв”Ѓв”Ѓ\u001b[0m\u001b[37mв”Ѓв”Ѓв”Ѓ\u001b[0m \u001b[1m0s\u001b[0m 186ms/step - accuracy: 0.7122 - loss: 1.4937"
        },
        {
          "type": "stream",
          "name": "stdout",
          "text": "\b\b\b\b\b\b\b\b\b\b\b\b\b\b\b\b\b\b\b\b\b\b\b\b\b\b\b\b\b\b\b\b\b\b\b\b\b\b\b\b\b\b\b\b\b\b\b\b\b\b\b\b\b\b\b\b\b\b\b\b\b\b\b\b\b\b\b\b\b\b\b\b\b\b\r\u001b[1m30/34\u001b[0m \u001b[32mв”Ѓв”Ѓв”Ѓв”Ѓв”Ѓв”Ѓв”Ѓв”Ѓв”Ѓв”Ѓв”Ѓв”Ѓв”Ѓв”Ѓв”Ѓв”Ѓв”Ѓ\u001b[0m\u001b[37mв”Ѓв”Ѓв”Ѓ\u001b[0m \u001b[1m0s\u001b[0m 183ms/step - accuracy: 0.7121 - loss: 1.4937"
        },
        {
          "type": "stream",
          "name": "stdout",
          "text": "\b\b\b\b\b\b\b\b\b\b\b\b\b\b\b\b\b\b\b\b\b\b\b\b\b\b\b\b\b\b\b\b\b\b\b\b\b\b\b\b\b\b\b\b\b\b\b\b\b\b\b\b\b\b\b\b\b\b\b\b\b\b\b\b\b\b\b\b\b\b\b\b\b\b\r\u001b[1m31/34\u001b[0m \u001b[32mв”Ѓв”Ѓв”Ѓв”Ѓв”Ѓв”Ѓв”Ѓв”Ѓв”Ѓв”Ѓв”Ѓв”Ѓв”Ѓв”Ѓв”Ѓв”Ѓв”Ѓв”Ѓ\u001b[0m\u001b[37mв”Ѓв”Ѓ\u001b[0m \u001b[1m0s\u001b[0m 180ms/step - accuracy: 0.7121 - loss: 1.4938"
        },
        {
          "type": "stream",
          "name": "stdout",
          "text": "\b\b\b\b\b\b\b\b\b\b\b\b\b\b\b\b\b\b\b\b\b\b\b\b\b\b\b\b\b\b\b\b\b\b\b\b\b\b\b\b\b\b\b\b\b\b\b\b\b\b\b\b\b\b\b\b\b\b\b\b\b\b\b\b\b\b\b\b\b\b\b\b\b\b\r\u001b[1m32/34\u001b[0m \u001b[32mв”Ѓв”Ѓв”Ѓв”Ѓв”Ѓв”Ѓв”Ѓв”Ѓв”Ѓв”Ѓв”Ѓв”Ѓв”Ѓв”Ѓв”Ѓв”Ѓв”Ѓв”Ѓ\u001b[0m\u001b[37mв”Ѓв”Ѓ\u001b[0m \u001b[1m0s\u001b[0m 178ms/step - accuracy: 0.7121 - loss: 1.4936"
        },
        {
          "type": "stream",
          "name": "stdout",
          "text": "\b\b\b\b\b\b\b\b\b\b\b\b\b\b\b\b\b\b\b\b\b\b\b\b\b\b\b\b\b\b\b\b\b\b\b\b\b\b\b\b\b\b\b\b\b\b\b\b\b\b\b\b\b\b\b\b\b\b\b\b\b\b\b\b\b\b\b\b\b\b\b\b\b\b\r\u001b[1m33/34\u001b[0m \u001b[32mв”Ѓв”Ѓв”Ѓв”Ѓв”Ѓв”Ѓв”Ѓв”Ѓв”Ѓв”Ѓв”Ѓв”Ѓв”Ѓв”Ѓв”Ѓв”Ѓв”Ѓв”Ѓв”Ѓ\u001b[0m\u001b[37mв”Ѓ\u001b[0m \u001b[1m0s\u001b[0m 175ms/step - accuracy: 0.7120 - loss: 1.4935"
        },
        {
          "type": "stream",
          "name": "stdout",
          "text": "\b\b\b\b\b\b\b\b\b\b\b\b\b\b\b\b\b\b\b\b\b\b\b\b\b\b\b\b\b\b\b\b\b\b\b\b\b\b\b\b\b\b\b\b\b\b\b\b\b\b\b\b\b\b\b\b\b\b\b\b\b\b\b\b\b\b\b\b\b\b\b\b\b\b\r\u001b[1m34/34\u001b[0m \u001b[32mв”Ѓв”Ѓв”Ѓв”Ѓв”Ѓв”Ѓв”Ѓв”Ѓв”Ѓв”Ѓв”Ѓв”Ѓв”Ѓв”Ѓв”Ѓв”Ѓв”Ѓв”Ѓв”Ѓв”Ѓ\u001b[0m\u001b[37m\u001b[0m \u001b[1m0s\u001b[0m 173ms/step - accuracy: 0.7120 - loss: 1.4936"
        },
        {
          "type": "stream",
          "name": "stdout",
          "text": "\b\b\b\b\b\b\b\b\b\b\b\b\b\b\b\b\b\b\b\b\b\b\b\b\b\b\b\b\b\b\b\b\b\b\b\b\b\b\b\b\b\b\b\b\b\b\b\b\b\b\b\b\b\b\b\b\b\b\b\b\b\b\b\b\b\b\b\b\b\b\b\b\b\b\r\u001b[1m34/34\u001b[0m \u001b[32mв”Ѓв”Ѓв”Ѓв”Ѓв”Ѓв”Ѓв”Ѓв”Ѓв”Ѓв”Ѓв”Ѓв”Ѓв”Ѓв”Ѓв”Ѓв”Ѓв”Ѓв”Ѓв”Ѓв”Ѓ\u001b[0m\u001b[37m\u001b[0m \u001b[1m10s\u001b[0m 300ms/step - accuracy: 0.7096 - loss: 1.4969 - val_accuracy: 0.7287 - val_loss: 1.6632\n"
        },
        {
          "type": "stream",
          "name": "stdout",
          "text": "Epoch 4/5\n"
        },
        {
          "type": "stream",
          "name": "stdout",
          "text": "\r\u001b[1m 1/34\u001b[0m \u001b[37mв”Ѓв”Ѓв”Ѓв”Ѓв”Ѓв”Ѓв”Ѓв”Ѓв”Ѓв”Ѓв”Ѓв”Ѓв”Ѓв”Ѓв”Ѓв”Ѓв”Ѓв”Ѓв”Ѓв”Ѓ\u001b[0m \u001b[1m9s\u001b[0m 287ms/step - accuracy: 0.7630 - loss: 1.2083"
        },
        {
          "type": "stream",
          "name": "stdout",
          "text": "\b\b\b\b\b\b\b\b\b\b\b\b\b\b\b\b\b\b\b\b\b\b\b\b\b\b\b\b\b\b\b\b\b\b\b\b\b\b\b\b\b\b\b\b\b\b\b\b\b\b\b\b\b\b\b\b\b\b\b\b\b\b\b\b\b\b\b\b\b\b\b\b\b\b\r\u001b[1m 2/34\u001b[0m \u001b[32mв”Ѓ\u001b[0m\u001b[37mв”Ѓв”Ѓв”Ѓв”Ѓв”Ѓв”Ѓв”Ѓв”Ѓв”Ѓв”Ѓв”Ѓв”Ѓв”Ѓв”Ѓв”Ѓв”Ѓв”Ѓв”Ѓв”Ѓ\u001b[0m \u001b[1m14s\u001b[0m 441ms/step - accuracy: 0.7551 - loss: 1.2635"
        },
        {
          "type": "stream",
          "name": "stdout",
          "text": "\b\b\b\b\b\b\b\b\b\b\b\b\b\b\b\b\b\b\b\b\b\b\b\b\b\b\b\b\b\b\b\b\b\b\b\b\b\b\b\b\b\b\b\b\b\b\b\b\b\b\b\b\b\b\b\b\b\b\b\b\b\b\b\b\b\b\b\b\b\b\b\b\b\b\b\r\u001b[1m 3/34\u001b[0m \u001b[32mв”Ѓ\u001b[0m\u001b[37mв”Ѓв”Ѓв”Ѓв”Ѓв”Ѓв”Ѓв”Ѓв”Ѓв”Ѓв”Ѓв”Ѓв”Ѓв”Ѓв”Ѓв”Ѓв”Ѓв”Ѓв”Ѓв”Ѓ\u001b[0m \u001b[1m11s\u001b[0m 357ms/step - accuracy: 0.7487 - loss: 1.3054"
        },
        {
          "type": "stream",
          "name": "stdout",
          "text": "\b\b\b\b\b\b\b\b\b\b\b\b\b\b\b\b\b\b\b\b\b\b\b\b\b\b\b\b\b\b\b\b\b\b\b\b\b\b\b\b\b\b\b\b\b\b\b\b\b\b\b\b\b\b\b\b\b\b\b\b\b\b\b\b\b\b\b\b\b\b\b\b\b\b\b\r\u001b[1m 4/34\u001b[0m \u001b[32mв”Ѓв”Ѓ\u001b[0m\u001b[37mв”Ѓв”Ѓв”Ѓв”Ѓв”Ѓв”Ѓв”Ѓв”Ѓв”Ѓв”Ѓв”Ѓв”Ѓв”Ѓв”Ѓв”Ѓв”Ѓв”Ѓв”Ѓ\u001b[0m \u001b[1m9s\u001b[0m 328ms/step - accuracy: 0.7477 - loss: 1.3136 "
        },
        {
          "type": "stream",
          "name": "stdout",
          "text": "\b\b\b\b\b\b\b\b\b\b\b\b\b\b\b\b\b\b\b\b\b\b\b\b\b\b\b\b\b\b\b\b\b\b\b\b\b\b\b\b\b\b\b\b\b\b\b\b\b\b\b\b\b\b\b\b\b\b\b\b\b\b\b\b\b\b\b\b\b\b\b\b\b\b\r\u001b[1m 5/34\u001b[0m \u001b[32mв”Ѓв”Ѓ\u001b[0m\u001b[37mв”Ѓв”Ѓв”Ѓв”Ѓв”Ѓв”Ѓв”Ѓв”Ѓв”Ѓв”Ѓв”Ѓв”Ѓв”Ѓв”Ѓв”Ѓв”Ѓв”Ѓв”Ѓ\u001b[0m \u001b[1m8s\u001b[0m 300ms/step - accuracy: 0.7442 - loss: 1.3286"
        },
        {
          "type": "stream",
          "name": "stdout",
          "text": "\b\b\b\b\b\b\b\b\b\b\b\b\b\b\b\b\b\b\b\b\b\b\b\b\b\b\b\b\b\b\b\b\b\b\b\b\b\b\b\b\b\b\b\b\b\b\b\b\b\b\b\b\b\b\b\b\b\b\b\b\b\b\b\b\b\b\b\b\b\b\b\b\b\b\r\u001b[1m 6/34\u001b[0m \u001b[32mв”Ѓв”Ѓв”Ѓ\u001b[0m\u001b[37mв”Ѓв”Ѓв”Ѓв”Ѓв”Ѓв”Ѓв”Ѓв”Ѓв”Ѓв”Ѓв”Ѓв”Ѓв”Ѓв”Ѓв”Ѓв”Ѓв”Ѓ\u001b[0m \u001b[1m7s\u001b[0m 277ms/step - accuracy: 0.7417 - loss: 1.3396"
        },
        {
          "type": "stream",
          "name": "stdout",
          "text": "\b\b\b\b\b\b\b\b\b\b\b\b\b\b\b\b\b\b\b\b\b\b\b\b\b\b\b\b\b\b\b\b\b\b\b\b\b\b\b\b\b\b\b\b\b\b\b\b\b\b\b\b\b\b\b\b\b\b\b\b\b\b\b\b\b\b\b\b\b\b\b\b\b\b\r\u001b[1m 7/34\u001b[0m \u001b[32mв”Ѓв”Ѓв”Ѓв”Ѓ\u001b[0m\u001b[37mв”Ѓв”Ѓв”Ѓв”Ѓв”Ѓв”Ѓв”Ѓв”Ѓв”Ѓв”Ѓв”Ѓв”Ѓв”Ѓв”Ѓв”Ѓв”Ѓ\u001b[0m \u001b[1m6s\u001b[0m 256ms/step - accuracy: 0.7381 - loss: 1.3543"
        },
        {
          "type": "stream",
          "name": "stdout",
          "text": "\b\b\b\b\b\b\b\b\b\b\b\b\b\b\b\b\b\b\b\b\b\b\b\b\b\b\b\b\b\b\b\b\b\b\b\b\b\b\b\b\b\b\b\b\b\b\b\b\b\b\b\b\b\b\b\b\b\b\b\b\b\b\b\b\b\b\b\b\b\b\b\b\b\b\r\u001b[1m 8/34\u001b[0m \u001b[32mв”Ѓв”Ѓв”Ѓв”Ѓ\u001b[0m\u001b[37mв”Ѓв”Ѓв”Ѓв”Ѓв”Ѓв”Ѓв”Ѓв”Ѓв”Ѓв”Ѓв”Ѓв”Ѓв”Ѓв”Ѓв”Ѓв”Ѓ\u001b[0m \u001b[1m6s\u001b[0m 243ms/step - accuracy: 0.7347 - loss: 1.3681"
        },
        {
          "type": "stream",
          "name": "stdout",
          "text": "\b\b\b\b\b\b\b\b\b\b\b\b\b\b\b\b\b\b\b\b\b\b\b\b\b\b\b\b\b\b\b\b\b\b\b\b\b\b\b\b\b\b\b\b\b\b\b\b\b\b\b\b\b\b\b\b\b\b\b\b\b\b\b\b\b\b\b\b\b\b\b\b\b\b\r\u001b[1m 9/34\u001b[0m \u001b[32mв”Ѓв”Ѓв”Ѓв”Ѓв”Ѓ\u001b[0m\u001b[37mв”Ѓв”Ѓв”Ѓв”Ѓв”Ѓв”Ѓв”Ѓв”Ѓв”Ѓв”Ѓв”Ѓв”Ѓв”Ѓв”Ѓв”Ѓ\u001b[0m \u001b[1m5s\u001b[0m 231ms/step - accuracy: 0.7320 - loss: 1.3791"
        },
        {
          "type": "stream",
          "name": "stdout",
          "text": "\b\b\b\b\b\b\b\b\b\b\b\b\b\b\b\b\b\b\b\b\b\b\b\b\b\b\b\b\b\b\b\b\b\b\b\b\b\b\b\b\b\b\b\b\b\b\b\b\b\b\b\b\b\b\b\b\b\b\b\b\b\b\b\b\b\b\b\b\b\b\b\b\b\b\r\u001b[1m10/34\u001b[0m \u001b[32mв”Ѓв”Ѓв”Ѓв”Ѓв”Ѓ\u001b[0m\u001b[37mв”Ѓв”Ѓв”Ѓв”Ѓв”Ѓв”Ѓв”Ѓв”Ѓв”Ѓв”Ѓв”Ѓв”Ѓв”Ѓв”Ѓв”Ѓ\u001b[0m \u001b[1m5s\u001b[0m 226ms/step - accuracy: 0.7299 - loss: 1.3868"
        },
        {
          "type": "stream",
          "name": "stdout",
          "text": "\b\b\b\b\b\b\b\b\b\b\b\b\b\b\b\b\b\b\b\b\b\b\b\b\b\b\b\b\b\b\b\b\b\b\b\b\b\b\b\b\b\b\b\b\b\b\b\b\b\b\b\b\b\b\b\b\b\b\b\b\b\b\b\b\b\b\b\b\b\b\b\b\b\b\r\u001b[1m11/34\u001b[0m \u001b[32mв”Ѓв”Ѓв”Ѓв”Ѓв”Ѓв”Ѓ\u001b[0m\u001b[37mв”Ѓв”Ѓв”Ѓв”Ѓв”Ѓв”Ѓв”Ѓв”Ѓв”Ѓв”Ѓв”Ѓв”Ѓв”Ѓв”Ѓ\u001b[0m \u001b[1m5s\u001b[0m 219ms/step - accuracy: 0.7282 - loss: 1.3926"
        },
        {
          "type": "stream",
          "name": "stdout",
          "text": "\b\b\b\b\b\b\b\b\b\b\b\b\b\b\b\b\b\b\b\b\b\b\b\b\b\b\b\b\b\b\b\b\b\b\b\b\b\b\b\b\b\b\b\b\b\b\b\b\b\b\b\b\b\b\b\b\b\b\b\b\b\b\b\b\b\b\b\b\b\b\b\b\b\b\r\u001b[1m12/34\u001b[0m \u001b[32mв”Ѓв”Ѓв”Ѓв”Ѓв”Ѓв”Ѓв”Ѓ\u001b[0m\u001b[37mв”Ѓв”Ѓв”Ѓв”Ѓв”Ѓв”Ѓв”Ѓв”Ѓв”Ѓв”Ѓв”Ѓв”Ѓв”Ѓ\u001b[0m \u001b[1m4s\u001b[0m 213ms/step - accuracy: 0.7268 - loss: 1.3969"
        },
        {
          "type": "stream",
          "name": "stdout",
          "text": "\b\b\b\b\b\b\b\b\b\b\b\b\b\b\b\b\b\b\b\b\b\b\b\b\b\b\b\b\b\b\b\b\b\b\b\b\b\b\b\b\b\b\b\b\b\b\b\b\b\b\b\b\b\b\b\b\b\b\b\b\b\b\b\b\b\b\b\b\b\b\b\b\b\b\r\u001b[1m13/34\u001b[0m \u001b[32mв”Ѓв”Ѓв”Ѓв”Ѓв”Ѓв”Ѓв”Ѓ\u001b[0m\u001b[37mв”Ѓв”Ѓв”Ѓв”Ѓв”Ѓв”Ѓв”Ѓв”Ѓв”Ѓв”Ѓв”Ѓв”Ѓв”Ѓ\u001b[0m \u001b[1m4s\u001b[0m 207ms/step - accuracy: 0.7256 - loss: 1.4009"
        },
        {
          "type": "stream",
          "name": "stdout",
          "text": "\b\b\b\b\b\b\b\b\b\b\b\b\b\b\b\b\b\b\b\b\b\b\b\b\b\b\b\b\b\b\b\b\b\b\b\b\b\b\b\b\b\b\b\b\b\b\b\b\b\b\b\b\b\b\b\b\b\b\b\b\b\b\b\b\b\b\b\b\b\b\b\b\b\b\r\u001b[1m14/34\u001b[0m \u001b[32mв”Ѓв”Ѓв”Ѓв”Ѓв”Ѓв”Ѓв”Ѓв”Ѓ\u001b[0m\u001b[37mв”Ѓв”Ѓв”Ѓв”Ѓв”Ѓв”Ѓв”Ѓв”Ѓв”Ѓв”Ѓв”Ѓв”Ѓ\u001b[0m \u001b[1m4s\u001b[0m 206ms/step - accuracy: 0.7246 - loss: 1.4043"
        },
        {
          "type": "stream",
          "name": "stdout",
          "text": "\b\b\b\b\b\b\b\b\b\b\b\b\b\b\b\b\b\b\b\b\b\b\b\b\b\b\b\b\b\b\b\b\b\b\b\b\b\b\b\b\b\b\b\b\b\b\b\b\b\b\b\b\b\b\b\b\b\b\b\b\b\b\b\b\b\b\b\b\b\b\b\b\b\b\r\u001b[1m15/34\u001b[0m \u001b[32mв”Ѓв”Ѓв”Ѓв”Ѓв”Ѓв”Ѓв”Ѓв”Ѓ\u001b[0m\u001b[37mв”Ѓв”Ѓв”Ѓв”Ѓв”Ѓв”Ѓв”Ѓв”Ѓв”Ѓв”Ѓв”Ѓв”Ѓ\u001b[0m \u001b[1m3s\u001b[0m 205ms/step - accuracy: 0.7235 - loss: 1.4082"
        },
        {
          "type": "stream",
          "name": "stdout",
          "text": "\b\b\b\b\b\b\b\b\b\b\b\b\b\b\b\b\b\b\b\b\b\b\b\b\b\b\b\b\b\b\b\b\b\b\b\b\b\b\b\b\b\b\b\b\b\b\b\b\b\b\b\b\b\b\b\b\b\b\b\b\b\b\b\b\b\b\b\b\b\b\b\b\b\b\r\u001b[1m16/34\u001b[0m \u001b[32mв”Ѓв”Ѓв”Ѓв”Ѓв”Ѓв”Ѓв”Ѓв”Ѓв”Ѓ\u001b[0m\u001b[37mв”Ѓв”Ѓв”Ѓв”Ѓв”Ѓв”Ѓв”Ѓв”Ѓв”Ѓв”Ѓв”Ѓ\u001b[0m \u001b[1m3s\u001b[0m 201ms/step - accuracy: 0.7229 - loss: 1.4099"
        },
        {
          "type": "stream",
          "name": "stdout",
          "text": "\b\b\b\b\b\b\b\b\b\b\b\b\b\b\b\b\b\b\b\b\b\b\b\b\b\b\b\b\b\b\b\b\b\b\b\b\b\b\b\b\b\b\b\b\b\b\b\b\b\b\b\b\b\b\b\b\b\b\b\b\b\b\b\b\b\b\b\b\b\b\b\b\b\b\r\u001b[1m17/34\u001b[0m \u001b[32mв”Ѓв”Ѓв”Ѓв”Ѓв”Ѓв”Ѓв”Ѓв”Ѓв”Ѓв”Ѓ\u001b[0m\u001b[37mв”Ѓв”Ѓв”Ѓв”Ѓв”Ѓв”Ѓв”Ѓв”Ѓв”Ѓв”Ѓ\u001b[0m \u001b[1m3s\u001b[0m 201ms/step - accuracy: 0.7223 - loss: 1.4116"
        },
        {
          "type": "stream",
          "name": "stdout",
          "text": "\b\b\b\b\b\b\b\b\b\b\b\b\b\b\b\b\b\b\b\b\b\b\b\b\b\b\b\b\b\b\b\b\b\b\b\b\b\b\b\b\b\b\b\b\b\b\b\b\b\b\b\b\b\b\b\b\b\b\b\b\b\b\b\b\b\b\b\b\b\b\b\b\b\b\r\u001b[1m18/34\u001b[0m \u001b[32mв”Ѓв”Ѓв”Ѓв”Ѓв”Ѓв”Ѓв”Ѓв”Ѓв”Ѓв”Ѓ\u001b[0m\u001b[37mв”Ѓв”Ѓв”Ѓв”Ѓв”Ѓв”Ѓв”Ѓв”Ѓв”Ѓв”Ѓ\u001b[0m \u001b[1m3s\u001b[0m 198ms/step - accuracy: 0.7219 - loss: 1.4131"
        },
        {
          "type": "stream",
          "name": "stdout",
          "text": "\b\b\b\b\b\b\b\b\b\b\b\b\b\b\b\b\b\b\b\b\b\b\b\b\b\b\b\b\b\b\b\b\b\b\b\b\b\b\b\b\b\b\b\b\b\b\b\b\b\b\b\b\b\b\b\b\b\b\b\b\b\b\b\b\b\b\b\b\b\b\b\b\b\b\r\u001b[1m19/34\u001b[0m \u001b[32mв”Ѓв”Ѓв”Ѓв”Ѓв”Ѓв”Ѓв”Ѓв”Ѓв”Ѓв”Ѓв”Ѓ\u001b[0m\u001b[37mв”Ѓв”Ѓв”Ѓв”Ѓв”Ѓв”Ѓв”Ѓв”Ѓв”Ѓ\u001b[0m \u001b[1m2s\u001b[0m 198ms/step - accuracy: 0.7215 - loss: 1.4145"
        },
        {
          "type": "stream",
          "name": "stdout",
          "text": "\b\b\b\b\b\b\b\b\b\b\b\b\b\b\b\b\b\b\b\b\b\b\b\b\b\b\b\b\b\b\b\b\b\b\b\b\b\b\b\b\b\b\b\b\b\b\b\b\b\b\b\b\b\b\b\b\b\b\b\b\b\b\b\b\b\b\b\b\b\b\b\b\b\b\r\u001b[1m20/34\u001b[0m \u001b[32mв”Ѓв”Ѓв”Ѓв”Ѓв”Ѓв”Ѓв”Ѓв”Ѓв”Ѓв”Ѓв”Ѓ\u001b[0m\u001b[37mв”Ѓв”Ѓв”Ѓв”Ѓв”Ѓв”Ѓв”Ѓв”Ѓв”Ѓ\u001b[0m \u001b[1m2s\u001b[0m 197ms/step - accuracy: 0.7211 - loss: 1.4157"
        },
        {
          "type": "stream",
          "name": "stdout",
          "text": "\b\b\b\b\b\b\b\b\b\b\b\b\b\b\b\b\b\b\b\b\b\b\b\b\b\b\b\b\b\b\b\b\b\b\b\b\b\b\b\b\b\b\b\b\b\b\b\b\b\b\b\b\b\b\b\b\b\b\b\b\b\b\b\b\b\b\b\b\b\b\b\b\b\b\r\u001b[1m21/34\u001b[0m \u001b[32mв”Ѓв”Ѓв”Ѓв”Ѓв”Ѓв”Ѓв”Ѓв”Ѓв”Ѓв”Ѓв”Ѓв”Ѓ\u001b[0m\u001b[37mв”Ѓв”Ѓв”Ѓв”Ѓв”Ѓв”Ѓв”Ѓв”Ѓ\u001b[0m \u001b[1m2s\u001b[0m 195ms/step - accuracy: 0.7208 - loss: 1.4167"
        },
        {
          "type": "stream",
          "name": "stdout",
          "text": "\b\b\b\b\b\b\b\b\b\b\b\b\b\b\b\b\b\b\b\b\b\b\b\b\b\b\b\b\b\b\b\b\b\b\b\b\b\b\b\b\b\b\b\b\b\b\b\b\b\b\b\b\b\b\b\b\b\b\b\b\b\b\b\b\b\b\b\b\b\b\b\b\b\b\r\u001b[1m22/34\u001b[0m \u001b[32mв”Ѓв”Ѓв”Ѓв”Ѓв”Ѓв”Ѓв”Ѓв”Ѓв”Ѓв”Ѓв”Ѓв”Ѓ\u001b[0m\u001b[37mв”Ѓв”Ѓв”Ѓв”Ѓв”Ѓв”Ѓв”Ѓв”Ѓ\u001b[0m \u001b[1m2s\u001b[0m 193ms/step - accuracy: 0.7205 - loss: 1.4181"
        },
        {
          "type": "stream",
          "name": "stdout",
          "text": "\b\b\b\b\b\b\b\b\b\b\b\b\b\b\b\b\b\b\b\b\b\b\b\b\b\b\b\b\b\b\b\b\b\b\b\b\b\b\b\b\b\b\b\b\b\b\b\b\b\b\b\b\b\b\b\b\b\b\b\b\b\b\b\b\b\b\b\b\b\b\b\b\b\b\r\u001b[1m23/34\u001b[0m \u001b[32mв”Ѓв”Ѓв”Ѓв”Ѓв”Ѓв”Ѓв”Ѓв”Ѓв”Ѓв”Ѓв”Ѓв”Ѓв”Ѓ\u001b[0m\u001b[37mв”Ѓв”Ѓв”Ѓв”Ѓв”Ѓв”Ѓв”Ѓ\u001b[0m \u001b[1m2s\u001b[0m 192ms/step - accuracy: 0.7200 - loss: 1.4200"
        },
        {
          "type": "stream",
          "name": "stdout",
          "text": "\b\b\b\b\b\b\b\b\b\b\b\b\b\b\b\b\b\b\b\b\b\b\b\b\b\b\b\b\b\b\b\b\b\b\b\b\b\b\b\b\b\b\b\b\b\b\b\b\b\b\b\b\b\b\b\b\b\b\b\b\b\b\b\b\b\b\b\b\b\b\b\b\b\b\r\u001b[1m24/34\u001b[0m \u001b[32mв”Ѓв”Ѓв”Ѓв”Ѓв”Ѓв”Ѓв”Ѓв”Ѓв”Ѓв”Ѓв”Ѓв”Ѓв”Ѓв”Ѓ\u001b[0m\u001b[37mв”Ѓв”Ѓв”Ѓв”Ѓв”Ѓв”Ѓ\u001b[0m \u001b[1m1s\u001b[0m 190ms/step - accuracy: 0.7196 - loss: 1.4217"
        },
        {
          "type": "stream",
          "name": "stdout",
          "text": "\b\b\b\b\b\b\b\b\b\b\b\b\b\b\b\b\b\b\b\b\b\b\b\b\b\b\b\b\b\b\b\b\b\b\b\b\b\b\b\b\b\b\b\b\b\b\b\b\b\b\b\b\b\b\b\b\b\b\b\b\b\b\b\b\b\b\b\b\b\b\b\b\b\b\r\u001b[1m25/34\u001b[0m \u001b[32mв”Ѓв”Ѓв”Ѓв”Ѓв”Ѓв”Ѓв”Ѓв”Ѓв”Ѓв”Ѓв”Ѓв”Ѓв”Ѓв”Ѓ\u001b[0m\u001b[37mв”Ѓв”Ѓв”Ѓв”Ѓв”Ѓв”Ѓ\u001b[0m \u001b[1m1s\u001b[0m 190ms/step - accuracy: 0.7193 - loss: 1.4233"
        },
        {
          "type": "stream",
          "name": "stdout",
          "text": "\b\b\b\b\b\b\b\b\b\b\b\b\b\b\b\b\b\b\b\b\b\b\b\b\b\b\b\b\b\b\b\b\b\b\b\b\b\b\b\b\b\b\b\b\b\b\b\b\b\b\b\b\b\b\b\b\b\b\b\b\b\b\b\b\b\b\b\b\b\b\b\b\b\b\r\u001b[1m26/34\u001b[0m \u001b[32mв”Ѓв”Ѓв”Ѓв”Ѓв”Ѓв”Ѓв”Ѓв”Ѓв”Ѓв”Ѓв”Ѓв”Ѓв”Ѓв”Ѓв”Ѓ\u001b[0m\u001b[37mв”Ѓв”Ѓв”Ѓв”Ѓв”Ѓ\u001b[0m \u001b[1m1s\u001b[0m 188ms/step - accuracy: 0.7189 - loss: 1.4250"
        },
        {
          "type": "stream",
          "name": "stdout",
          "text": "\b\b\b\b\b\b\b\b\b\b\b\b\b\b\b\b\b\b\b\b\b\b\b\b\b\b\b\b\b\b\b\b\b\b\b\b\b\b\b\b\b\b\b\b\b\b\b\b\b\b\b\b\b\b\b\b\b\b\b\b\b\b\b\b\b\b\b\b\b\b\b\b\b\b\r\u001b[1m27/34\u001b[0m \u001b[32mв”Ѓв”Ѓв”Ѓв”Ѓв”Ѓв”Ѓв”Ѓв”Ѓв”Ѓв”Ѓв”Ѓв”Ѓв”Ѓв”Ѓв”Ѓ\u001b[0m\u001b[37mв”Ѓв”Ѓв”Ѓв”Ѓв”Ѓ\u001b[0m \u001b[1m1s\u001b[0m 187ms/step - accuracy: 0.7184 - loss: 1.4268"
        },
        {
          "type": "stream",
          "name": "stdout",
          "text": "\b\b\b\b\b\b\b\b\b\b\b\b\b\b\b\b\b\b\b\b\b\b\b\b\b\b\b\b\b\b\b\b\b\b\b\b\b\b\b\b\b\b\b\b\b\b\b\b\b\b\b\b\b\b\b\b\b\b\b\b\b\b\b\b\b\b\b\b\b\b\b\b\b\b\r\u001b[1m28/34\u001b[0m \u001b[32mв”Ѓв”Ѓв”Ѓв”Ѓв”Ѓв”Ѓв”Ѓв”Ѓв”Ѓв”Ѓв”Ѓв”Ѓв”Ѓв”Ѓв”Ѓв”Ѓ\u001b[0m\u001b[37mв”Ѓв”Ѓв”Ѓв”Ѓ\u001b[0m \u001b[1m1s\u001b[0m 184ms/step - accuracy: 0.7180 - loss: 1.4285"
        },
        {
          "type": "stream",
          "name": "stdout",
          "text": "\b\b\b\b\b\b\b\b\b\b\b\b\b\b\b\b\b\b\b\b\b\b\b\b\b\b\b\b\b\b\b\b\b\b\b\b\b\b\b\b\b\b\b\b\b\b\b\b\b\b\b\b\b\b\b\b\b\b\b\b\b\b\b\b\b\b\b\b\b\b\b\b\b\b\r\u001b[1m29/34\u001b[0m \u001b[32mв”Ѓв”Ѓв”Ѓв”Ѓв”Ѓв”Ѓв”Ѓв”Ѓв”Ѓв”Ѓв”Ѓв”Ѓв”Ѓв”Ѓв”Ѓв”Ѓв”Ѓ\u001b[0m\u001b[37mв”Ѓв”Ѓв”Ѓ\u001b[0m \u001b[1m0s\u001b[0m 181ms/step - accuracy: 0.7175 - loss: 1.4301"
        },
        {
          "type": "stream",
          "name": "stdout",
          "text": "\b\b\b\b\b\b\b\b\b\b\b\b\b\b\b\b\b\b\b\b\b\b\b\b\b\b\b\b\b\b\b\b\b\b\b\b\b\b\b\b\b\b\b\b\b\b\b\b\b\b\b\b\b\b\b\b\b\b\b\b\b\b\b\b\b\b\b\b\b\b\b\b\b\b\r\u001b[1m30/34\u001b[0m \u001b[32mв”Ѓв”Ѓв”Ѓв”Ѓв”Ѓв”Ѓв”Ѓв”Ѓв”Ѓв”Ѓв”Ѓв”Ѓв”Ѓв”Ѓв”Ѓв”Ѓв”Ѓ\u001b[0m\u001b[37mв”Ѓв”Ѓв”Ѓ\u001b[0m \u001b[1m0s\u001b[0m 178ms/step - accuracy: 0.7171 - loss: 1.4315"
        },
        {
          "type": "stream",
          "name": "stdout",
          "text": "\b\b\b\b\b\b\b\b\b\b\b\b\b\b\b\b\b\b\b\b\b\b\b\b\b\b\b\b\b\b\b\b\b\b\b\b\b\b\b\b\b\b\b\b\b\b\b\b\b\b\b\b\b\b\b\b\b\b\b\b\b\b\b\b\b\b\b\b\b\b\b\b\b\b\r\u001b[1m31/34\u001b[0m \u001b[32mв”Ѓв”Ѓв”Ѓв”Ѓв”Ѓв”Ѓв”Ѓв”Ѓв”Ѓв”Ѓв”Ѓв”Ѓв”Ѓв”Ѓв”Ѓв”Ѓв”Ѓв”Ѓ\u001b[0m\u001b[37mв”Ѓв”Ѓ\u001b[0m \u001b[1m0s\u001b[0m 176ms/step - accuracy: 0.7168 - loss: 1.4327"
        },
        {
          "type": "stream",
          "name": "stdout",
          "text": "\b\b\b\b\b\b\b\b\b\b\b\b\b\b\b\b\b\b\b\b\b\b\b\b\b\b\b\b\b\b\b\b\b\b\b\b\b\b\b\b\b\b\b\b\b\b\b\b\b\b\b\b\b\b\b\b\b\b\b\b\b\b\b\b\b\b\b\b\b\b\b\b\b\b\r\u001b[1m32/34\u001b[0m \u001b[32mв”Ѓв”Ѓв”Ѓв”Ѓв”Ѓв”Ѓв”Ѓв”Ѓв”Ѓв”Ѓв”Ѓв”Ѓв”Ѓв”Ѓв”Ѓв”Ѓв”Ѓв”Ѓ\u001b[0m\u001b[37mв”Ѓв”Ѓ\u001b[0m \u001b[1m0s\u001b[0m 174ms/step - accuracy: 0.7164 - loss: 1.4338"
        },
        {
          "type": "stream",
          "name": "stdout",
          "text": "\b\b\b\b\b\b\b\b\b\b\b\b\b\b\b\b\b\b\b\b\b\b\b\b\b\b\b\b\b\b\b\b\b\b\b\b\b\b\b\b\b\b\b\b\b\b\b\b\b\b\b\b\b\b\b\b\b\b\b\b\b\b\b\b\b\b\b\b\b\b\b\b\b\b\r\u001b[1m33/34\u001b[0m \u001b[32mв”Ѓв”Ѓв”Ѓв”Ѓв”Ѓв”Ѓв”Ѓв”Ѓв”Ѓв”Ѓв”Ѓв”Ѓв”Ѓв”Ѓв”Ѓв”Ѓв”Ѓв”Ѓв”Ѓ\u001b[0m\u001b[37mв”Ѓ\u001b[0m \u001b[1m0s\u001b[0m 171ms/step - accuracy: 0.7162 - loss: 1.4345"
        },
        {
          "type": "stream",
          "name": "stdout",
          "text": "\b\b\b\b\b\b\b\b\b\b\b\b\b\b\b\b\b\b\b\b\b\b\b\b\b\b\b\b\b\b\b\b\b\b\b\b\b\b\b\b\b\b\b\b\b\b\b\b\b\b\b\b\b\b\b\b\b\b\b\b\b\b\b\b\b\b\b\b\b\b\b\b\b\b\r\u001b[1m34/34\u001b[0m \u001b[32mв”Ѓв”Ѓв”Ѓв”Ѓв”Ѓв”Ѓв”Ѓв”Ѓв”Ѓв”Ѓв”Ѓв”Ѓв”Ѓв”Ѓв”Ѓв”Ѓв”Ѓв”Ѓв”Ѓв”Ѓ\u001b[0m\u001b[37m\u001b[0m \u001b[1m0s\u001b[0m 169ms/step - accuracy: 0.7160 - loss: 1.4352"
        },
        {
          "type": "stream",
          "name": "stdout",
          "text": "\b\b\b\b\b\b\b\b\b\b\b\b\b\b\b\b\b\b\b\b\b\b\b\b\b\b\b\b\b\b\b\b\b\b\b\b\b\b\b\b\b\b\b\b\b\b\b\b\b\b\b\b\b\b\b\b\b\b\b\b\b\b\b\b\b\b\b\b\b\b\b\b\b\b\r\u001b[1m34/34\u001b[0m \u001b[32mв”Ѓв”Ѓв”Ѓв”Ѓв”Ѓв”Ѓв”Ѓв”Ѓв”Ѓв”Ѓв”Ѓв”Ѓв”Ѓв”Ѓв”Ѓв”Ѓв”Ѓв”Ѓв”Ѓв”Ѓ\u001b[0m\u001b[37m\u001b[0m \u001b[1m10s\u001b[0m 292ms/step - accuracy: 0.7079 - loss: 1.4580 - val_accuracy: 0.7288 - val_loss: 1.5005\n"
        },
        {
          "type": "stream",
          "name": "stdout",
          "text": "Epoch 5/5\n"
        },
        {
          "type": "stream",
          "name": "stdout",
          "text": "\r\u001b[1m 1/34\u001b[0m \u001b[37mв”Ѓв”Ѓв”Ѓв”Ѓв”Ѓв”Ѓв”Ѓв”Ѓв”Ѓв”Ѓв”Ѓв”Ѓв”Ѓв”Ѓв”Ѓв”Ѓв”Ѓв”Ѓв”Ѓв”Ѓ\u001b[0m \u001b[1m9s\u001b[0m 284ms/step - accuracy: 0.7220 - loss: 1.2720"
        },
        {
          "type": "stream",
          "name": "stdout",
          "text": "\b\b\b\b\b\b\b\b\b\b\b\b\b\b\b\b\b\b\b\b\b\b\b\b\b\b\b\b\b\b\b\b\b\b\b\b\b\b\b\b\b\b\b\b\b\b\b\b\b\b\b\b\b\b\b\b\b\b\b\b\b\b\b\b\b\b\b\b\b\b\b\b\b\b\r\u001b[1m 2/34\u001b[0m \u001b[32mв”Ѓ\u001b[0m\u001b[37mв”Ѓв”Ѓв”Ѓв”Ѓв”Ѓв”Ѓв”Ѓв”Ѓв”Ѓв”Ѓв”Ѓв”Ѓв”Ѓв”Ѓв”Ѓв”Ѓв”Ѓв”Ѓв”Ѓ\u001b[0m \u001b[1m10s\u001b[0m 339ms/step - accuracy: 0.7192 - loss: 1.3152"
        },
        {
          "type": "stream",
          "name": "stdout",
          "text": "\b\b\b\b\b\b\b\b\b\b\b\b\b\b\b\b\b\b\b\b\b\b\b\b\b\b\b\b\b\b\b\b\b\b\b\b\b\b\b\b\b\b\b\b\b\b\b\b\b\b\b\b\b\b\b\b\b\b\b\b\b\b\b\b\b\b\b\b\b\b\b\b\b\b\b\r\u001b[1m 3/34\u001b[0m \u001b[32mв”Ѓ\u001b[0m\u001b[37mв”Ѓв”Ѓв”Ѓв”Ѓв”Ѓв”Ѓв”Ѓв”Ѓв”Ѓв”Ѓв”Ѓв”Ѓв”Ѓв”Ѓв”Ѓв”Ѓв”Ѓв”Ѓв”Ѓ\u001b[0m \u001b[1m8s\u001b[0m 288ms/step - accuracy: 0.7102 - loss: 1.3609 "
        },
        {
          "type": "stream",
          "name": "stdout",
          "text": "\b\b\b\b\b\b\b\b\b\b\b\b\b\b\b\b\b\b\b\b\b\b\b\b\b\b\b\b\b\b\b\b\b\b\b\b\b\b\b\b\b\b\b\b\b\b\b\b\b\b\b\b\b\b\b\b\b\b\b\b\b\b\b\b\b\b\b\b\b\b\b\b\b\b\r\u001b[1m 4/34\u001b[0m \u001b[32mв”Ѓв”Ѓ\u001b[0m\u001b[37mв”Ѓв”Ѓв”Ѓв”Ѓв”Ѓв”Ѓв”Ѓв”Ѓв”Ѓв”Ѓв”Ѓв”Ѓв”Ѓв”Ѓв”Ѓв”Ѓв”Ѓв”Ѓ\u001b[0m \u001b[1m8s\u001b[0m 276ms/step - accuracy: 0.7070 - loss: 1.3780"
        },
        {
          "type": "stream",
          "name": "stdout",
          "text": "\b\b\b\b\b\b\b\b\b\b\b\b\b\b\b\b\b\b\b\b\b\b\b\b\b\b\b\b\b\b\b\b\b\b\b\b\b\b\b\b\b\b\b\b\b\b\b\b\b\b\b\b\b\b\b\b\b\b\b\b\b\b\b\b\b\b\b\b\b\b\b\b\b\b\r\u001b[1m 5/34\u001b[0m \u001b[32mв”Ѓв”Ѓ\u001b[0m\u001b[37mв”Ѓв”Ѓв”Ѓв”Ѓв”Ѓв”Ѓв”Ѓв”Ѓв”Ѓв”Ѓв”Ѓв”Ѓв”Ѓв”Ѓв”Ѓв”Ѓв”Ѓв”Ѓ\u001b[0m \u001b[1m7s\u001b[0m 261ms/step - accuracy: 0.7069 - loss: 1.3831"
        },
        {
          "type": "stream",
          "name": "stdout",
          "text": "\b\b\b\b\b\b\b\b\b\b\b\b\b\b\b\b\b\b\b\b\b\b\b\b\b\b\b\b\b\b\b\b\b\b\b\b\b\b\b\b\b\b\b\b\b\b\b\b\b\b\b\b\b\b\b\b\b\b\b\b\b\b\b\b\b\b\b\b\b\b\b\b\b\b\r\u001b[1m 6/34\u001b[0m \u001b[32mв”Ѓв”Ѓв”Ѓ\u001b[0m\u001b[37mв”Ѓв”Ѓв”Ѓв”Ѓв”Ѓв”Ѓв”Ѓв”Ѓв”Ѓв”Ѓв”Ѓв”Ѓв”Ѓв”Ѓв”Ѓв”Ѓв”Ѓ\u001b[0m \u001b[1m6s\u001b[0m 249ms/step - accuracy: 0.7066 - loss: 1.3896"
        },
        {
          "type": "stream",
          "name": "stdout",
          "text": "\b\b\b\b\b\b\b\b\b\b\b\b\b\b\b\b\b\b\b\b\b\b\b\b\b\b\b\b\b\b\b\b\b\b\b\b\b\b\b\b\b\b\b\b\b\b\b\b\b\b\b\b\b\b\b\b\b\b\b\b\b\b\b\b\b\b\b\b\b\b\b\b\b\b\r\u001b[1m 7/34\u001b[0m \u001b[32mв”Ѓв”Ѓв”Ѓв”Ѓ\u001b[0m\u001b[37mв”Ѓв”Ѓв”Ѓв”Ѓв”Ѓв”Ѓв”Ѓв”Ѓв”Ѓв”Ѓв”Ѓв”Ѓв”Ѓв”Ѓв”Ѓв”Ѓ\u001b[0m \u001b[1m6s\u001b[0m 237ms/step - accuracy: 0.7067 - loss: 1.3947"
        },
        {
          "type": "stream",
          "name": "stdout",
          "text": "\b\b\b\b\b\b\b\b\b\b\b\b\b\b\b\b\b\b\b\b\b\b\b\b\b\b\b\b\b\b\b\b\b\b\b\b\b\b\b\b\b\b\b\b\b\b\b\b\b\b\b\b\b\b\b\b\b\b\b\b\b\b\b\b\b\b\b\b\b\b\b\b\b\b\r\u001b[1m 8/34\u001b[0m \u001b[32mв”Ѓв”Ѓв”Ѓв”Ѓ\u001b[0m\u001b[37mв”Ѓв”Ѓв”Ѓв”Ѓв”Ѓв”Ѓв”Ѓв”Ѓв”Ѓв”Ѓв”Ѓв”Ѓв”Ѓв”Ѓв”Ѓв”Ѓ\u001b[0m \u001b[1m5s\u001b[0m 230ms/step - accuracy: 0.7069 - loss: 1.3993"
        },
        {
          "type": "stream",
          "name": "stdout",
          "text": "\b\b\b\b\b\b\b\b\b\b\b\b\b\b\b\b\b\b\b\b\b\b\b\b\b\b\b\b\b\b\b\b\b\b\b\b\b\b\b\b\b\b\b\b\b\b\b\b\b\b\b\b\b\b\b\b\b\b\b\b\b\b\b\b\b\b\b\b\b\b\b\b\b\b\r\u001b[1m 9/34\u001b[0m \u001b[32mв”Ѓв”Ѓв”Ѓв”Ѓв”Ѓ\u001b[0m\u001b[37mв”Ѓв”Ѓв”Ѓв”Ѓв”Ѓв”Ѓв”Ѓв”Ѓв”Ѓв”Ѓв”Ѓв”Ѓв”Ѓв”Ѓв”Ѓ\u001b[0m \u001b[1m5s\u001b[0m 220ms/step - accuracy: 0.7072 - loss: 1.4020"
        },
        {
          "type": "stream",
          "name": "stdout",
          "text": "\b\b\b\b\b\b\b\b\b\b\b\b\b\b\b\b\b\b\b\b\b\b\b\b\b\b\b\b\b\b\b\b\b\b\b\b\b\b\b\b\b\b\b\b\b\b\b\b\b\b\b\b\b\b\b\b\b\b\b\b\b\b\b\b\b\b\b\b\b\b\b\b\b\b\r\u001b[1m10/34\u001b[0m \u001b[32mв”Ѓв”Ѓв”Ѓв”Ѓв”Ѓ\u001b[0m\u001b[37mв”Ѓв”Ѓв”Ѓв”Ѓв”Ѓв”Ѓв”Ѓв”Ѓв”Ѓв”Ѓв”Ѓв”Ѓв”Ѓв”Ѓв”Ѓ\u001b[0m \u001b[1m5s\u001b[0m 212ms/step - accuracy: 0.7074 - loss: 1.4037"
        },
        {
          "type": "stream",
          "name": "stdout",
          "text": "\b\b\b\b\b\b\b\b\b\b\b\b\b\b\b\b\b\b\b\b\b\b\b\b\b\b\b\b\b\b\b\b\b\b\b\b\b\b\b\b\b\b\b\b\b\b\b\b\b\b\b\b\b\b\b\b\b\b\b\b\b\b\b\b\b\b\b\b\b\b\b\b\b\b\r\u001b[1m11/34\u001b[0m \u001b[32mв”Ѓв”Ѓв”Ѓв”Ѓв”Ѓв”Ѓ\u001b[0m\u001b[37mв”Ѓв”Ѓв”Ѓв”Ѓв”Ѓв”Ѓв”Ѓв”Ѓв”Ѓв”Ѓв”Ѓв”Ѓв”Ѓв”Ѓ\u001b[0m \u001b[1m4s\u001b[0m 207ms/step - accuracy: 0.7078 - loss: 1.4040"
        },
        {
          "type": "stream",
          "name": "stdout",
          "text": "\b\b\b\b\b\b\b\b\b\b\b\b\b\b\b\b\b\b\b\b\b\b\b\b\b\b\b\b\b\b\b\b\b\b\b\b\b\b\b\b\b\b\b\b\b\b\b\b\b\b\b\b\b\b\b\b\b\b\b\b\b\b\b\b\b\b\b\b\b\b\b\b\b\b\r\u001b[1m12/34\u001b[0m \u001b[32mв”Ѓв”Ѓв”Ѓв”Ѓв”Ѓв”Ѓв”Ѓ\u001b[0m\u001b[37mв”Ѓв”Ѓв”Ѓв”Ѓв”Ѓв”Ѓв”Ѓв”Ѓв”Ѓв”Ѓв”Ѓв”Ѓв”Ѓ\u001b[0m \u001b[1m4s\u001b[0m 201ms/step - accuracy: 0.7081 - loss: 1.4050"
        },
        {
          "type": "stream",
          "name": "stdout",
          "text": "\b\b\b\b\b\b\b\b\b\b\b\b\b\b\b\b\b\b\b\b\b\b\b\b\b\b\b\b\b\b\b\b\b\b\b\b\b\b\b\b\b\b\b\b\b\b\b\b\b\b\b\b\b\b\b\b\b\b\b\b\b\b\b\b\b\b\b\b\b\b\b\b\b\b\r\u001b[1m13/34\u001b[0m \u001b[32mв”Ѓв”Ѓв”Ѓв”Ѓв”Ѓв”Ѓв”Ѓ\u001b[0m\u001b[37mв”Ѓв”Ѓв”Ѓв”Ѓв”Ѓв”Ѓв”Ѓв”Ѓв”Ѓв”Ѓв”Ѓв”Ѓв”Ѓ\u001b[0m \u001b[1m4s\u001b[0m 198ms/step - accuracy: 0.7086 - loss: 1.4049"
        },
        {
          "type": "stream",
          "name": "stdout",
          "text": "\b\b\b\b\b\b\b\b\b\b\b\b\b\b\b\b\b\b\b\b\b\b\b\b\b\b\b\b\b\b\b\b\b\b\b\b\b\b\b\b\b\b\b\b\b\b\b\b\b\b\b\b\b\b\b\b\b\b\b\b\b\b\b\b\b\b\b\b\b\b\b\b\b\b\r\u001b[1m14/34\u001b[0m \u001b[32mв”Ѓв”Ѓв”Ѓв”Ѓв”Ѓв”Ѓв”Ѓв”Ѓ\u001b[0m\u001b[37mв”Ѓв”Ѓв”Ѓв”Ѓв”Ѓв”Ѓв”Ѓв”Ѓв”Ѓв”Ѓв”Ѓв”Ѓ\u001b[0m \u001b[1m3s\u001b[0m 194ms/step - accuracy: 0.7091 - loss: 1.4047"
        },
        {
          "type": "stream",
          "name": "stdout",
          "text": "\b\b\b\b\b\b\b\b\b\b\b\b\b\b\b\b\b\b\b\b\b\b\b\b\b\b\b\b\b\b\b\b\b\b\b\b\b\b\b\b\b\b\b\b\b\b\b\b\b\b\b\b\b\b\b\b\b\b\b\b\b\b\b\b\b\b\b\b\b\b\b\b\b\b\r\u001b[1m15/34\u001b[0m \u001b[32mв”Ѓв”Ѓв”Ѓв”Ѓв”Ѓв”Ѓв”Ѓв”Ѓ\u001b[0m\u001b[37mв”Ѓв”Ѓв”Ѓв”Ѓв”Ѓв”Ѓв”Ѓв”Ѓв”Ѓв”Ѓв”Ѓв”Ѓ\u001b[0m \u001b[1m3s\u001b[0m 192ms/step - accuracy: 0.7097 - loss: 1.4041"
        },
        {
          "type": "stream",
          "name": "stdout",
          "text": "\b\b\b\b\b\b\b\b\b\b\b\b\b\b\b\b\b\b\b\b\b\b\b\b\b\b\b\b\b\b\b\b\b\b\b\b\b\b\b\b\b\b\b\b\b\b\b\b\b\b\b\b\b\b\b\b\b\b\b\b\b\b\b\b\b\b\b\b\b\b\b\b\b\b\r\u001b[1m16/34\u001b[0m \u001b[32mв”Ѓв”Ѓв”Ѓв”Ѓв”Ѓв”Ѓв”Ѓв”Ѓв”Ѓ\u001b[0m\u001b[37mв”Ѓв”Ѓв”Ѓв”Ѓв”Ѓв”Ѓв”Ѓв”Ѓв”Ѓв”Ѓв”Ѓ\u001b[0m \u001b[1m3s\u001b[0m 193ms/step - accuracy: 0.7101 - loss: 1.4040"
        },
        {
          "type": "stream",
          "name": "stdout",
          "text": "\b\b\b\b\b\b\b\b\b\b\b\b\b\b\b\b\b\b\b\b\b\b\b\b\b\b\b\b\b\b\b\b\b\b\b\b\b\b\b\b\b\b\b\b\b\b\b\b\b\b\b\b\b\b\b\b\b\b\b\b\b\b\b\b\b\b\b\b\b\b\b\b\b\b\r\u001b[1m17/34\u001b[0m \u001b[32mв”Ѓв”Ѓв”Ѓв”Ѓв”Ѓв”Ѓв”Ѓв”Ѓв”Ѓв”Ѓ\u001b[0m\u001b[37mв”Ѓв”Ѓв”Ѓв”Ѓв”Ѓв”Ѓв”Ѓв”Ѓв”Ѓв”Ѓ\u001b[0m \u001b[1m3s\u001b[0m 192ms/step - accuracy: 0.7105 - loss: 1.4040"
        },
        {
          "type": "stream",
          "name": "stdout",
          "text": "\b\b\b\b\b\b\b\b\b\b\b\b\b\b\b\b\b\b\b\b\b\b\b\b\b\b\b\b\b\b\b\b\b\b\b\b\b\b\b\b\b\b\b\b\b\b\b\b\b\b\b\b\b\b\b\b\b\b\b\b\b\b\b\b\b\b\b\b\b\b\b\b\b\b\r\u001b[1m18/34\u001b[0m \u001b[32mв”Ѓв”Ѓв”Ѓв”Ѓв”Ѓв”Ѓв”Ѓв”Ѓв”Ѓв”Ѓ\u001b[0m\u001b[37mв”Ѓв”Ѓв”Ѓв”Ѓв”Ѓв”Ѓв”Ѓв”Ѓв”Ѓв”Ѓ\u001b[0m \u001b[1m3s\u001b[0m 191ms/step - accuracy: 0.7108 - loss: 1.4038"
        },
        {
          "type": "stream",
          "name": "stdout",
          "text": "\b\b\b\b\b\b\b\b\b\b\b\b\b\b\b\b\b\b\b\b\b\b\b\b\b\b\b\b\b\b\b\b\b\b\b\b\b\b\b\b\b\b\b\b\b\b\b\b\b\b\b\b\b\b\b\b\b\b\b\b\b\b\b\b\b\b\b\b\b\b\b\b\b\b\r\u001b[1m19/34\u001b[0m \u001b[32mв”Ѓв”Ѓв”Ѓв”Ѓв”Ѓв”Ѓв”Ѓв”Ѓв”Ѓв”Ѓв”Ѓ\u001b[0m\u001b[37mв”Ѓв”Ѓв”Ѓв”Ѓв”Ѓв”Ѓв”Ѓв”Ѓв”Ѓ\u001b[0m \u001b[1m2s\u001b[0m 189ms/step - accuracy: 0.7111 - loss: 1.4033"
        },
        {
          "type": "stream",
          "name": "stdout",
          "text": "\b\b\b\b\b\b\b\b\b\b\b\b\b\b\b\b\b\b\b\b\b\b\b\b\b\b\b\b\b\b\b\b\b\b\b\b\b\b\b\b\b\b\b\b\b\b\b\b\b\b\b\b\b\b\b\b\b\b\b\b\b\b\b\b\b\b\b\b\b\b\b\b\b\b\r\u001b[1m20/34\u001b[0m \u001b[32mв”Ѓв”Ѓв”Ѓв”Ѓв”Ѓв”Ѓв”Ѓв”Ѓв”Ѓв”Ѓв”Ѓ\u001b[0m\u001b[37mв”Ѓв”Ѓв”Ѓв”Ѓв”Ѓв”Ѓв”Ѓв”Ѓв”Ѓ\u001b[0m \u001b[1m2s\u001b[0m 187ms/step - accuracy: 0.7113 - loss: 1.4035"
        },
        {
          "type": "stream",
          "name": "stdout",
          "text": "\b\b\b\b\b\b\b\b\b\b\b\b\b\b\b\b\b\b\b\b\b\b\b\b\b\b\b\b\b\b\b\b\b\b\b\b\b\b\b\b\b\b\b\b\b\b\b\b\b\b\b\b\b\b\b\b\b\b\b\b\b\b\b\b\b\b\b\b\b\b\b\b\b\b\r\u001b[1m21/34\u001b[0m \u001b[32mв”Ѓв”Ѓв”Ѓв”Ѓв”Ѓв”Ѓв”Ѓв”Ѓв”Ѓв”Ѓв”Ѓв”Ѓ\u001b[0m\u001b[37mв”Ѓв”Ѓв”Ѓв”Ѓв”Ѓв”Ѓв”Ѓв”Ѓ\u001b[0m \u001b[1m2s\u001b[0m 184ms/step - accuracy: 0.7115 - loss: 1.4032"
        },
        {
          "type": "stream",
          "name": "stdout",
          "text": "\b\b\b\b\b\b\b\b\b\b\b\b\b\b\b\b\b\b\b\b\b\b\b\b\b\b\b\b\b\b\b\b\b\b\b\b\b\b\b\b\b\b\b\b\b\b\b\b\b\b\b\b\b\b\b\b\b\b\b\b\b\b\b\b\b\b\b\b\b\b\b\b\b\b\r\u001b[1m22/34\u001b[0m \u001b[32mв”Ѓв”Ѓв”Ѓв”Ѓв”Ѓв”Ѓв”Ѓв”Ѓв”Ѓв”Ѓв”Ѓв”Ѓ\u001b[0m\u001b[37mв”Ѓв”Ѓв”Ѓв”Ѓв”Ѓв”Ѓв”Ѓв”Ѓ\u001b[0m \u001b[1m2s\u001b[0m 184ms/step - accuracy: 0.7117 - loss: 1.4032"
        },
        {
          "type": "stream",
          "name": "stdout",
          "text": "\b\b\b\b\b\b\b\b\b\b\b\b\b\b\b\b\b\b\b\b\b\b\b\b\b\b\b\b\b\b\b\b\b\b\b\b\b\b\b\b\b\b\b\b\b\b\b\b\b\b\b\b\b\b\b\b\b\b\b\b\b\b\b\b\b\b\b\b\b\b\b\b\b\b\r\u001b[1m23/34\u001b[0m \u001b[32mв”Ѓв”Ѓв”Ѓв”Ѓв”Ѓв”Ѓв”Ѓв”Ѓв”Ѓв”Ѓв”Ѓв”Ѓв”Ѓ\u001b[0m\u001b[37mв”Ѓв”Ѓв”Ѓв”Ѓв”Ѓв”Ѓв”Ѓ\u001b[0m \u001b[1m2s\u001b[0m 182ms/step - accuracy: 0.7118 - loss: 1.4034"
        },
        {
          "type": "stream",
          "name": "stdout",
          "text": "\b\b\b\b\b\b\b\b\b\b\b\b\b\b\b\b\b\b\b\b\b\b\b\b\b\b\b\b\b\b\b\b\b\b\b\b\b\b\b\b\b\b\b\b\b\b\b\b\b\b\b\b\b\b\b\b\b\b\b\b\b\b\b\b\b\b\b\b\b\b\b\b\b\b\r\u001b[1m24/34\u001b[0m \u001b[32mв”Ѓв”Ѓв”Ѓв”Ѓв”Ѓв”Ѓв”Ѓв”Ѓв”Ѓв”Ѓв”Ѓв”Ѓв”Ѓв”Ѓ\u001b[0m\u001b[37mв”Ѓв”Ѓв”Ѓв”Ѓв”Ѓв”Ѓ\u001b[0m \u001b[1m1s\u001b[0m 180ms/step - accuracy: 0.7119 - loss: 1.4040"
        },
        {
          "type": "stream",
          "name": "stdout",
          "text": "\b\b\b\b\b\b\b\b\b\b\b\b\b\b\b\b\b\b\b\b\b\b\b\b\b\b\b\b\b\b\b\b\b\b\b\b\b\b\b\b\b\b\b\b\b\b\b\b\b\b\b\b\b\b\b\b\b\b\b\b\b\b\b\b\b\b\b\b\b\b\b\b\b\b\r\u001b[1m25/34\u001b[0m \u001b[32mв”Ѓв”Ѓв”Ѓв”Ѓв”Ѓв”Ѓв”Ѓв”Ѓв”Ѓв”Ѓв”Ѓв”Ѓв”Ѓв”Ѓ\u001b[0m\u001b[37mв”Ѓв”Ѓв”Ѓв”Ѓв”Ѓв”Ѓ\u001b[0m \u001b[1m1s\u001b[0m 180ms/step - accuracy: 0.7120 - loss: 1.4044"
        },
        {
          "type": "stream",
          "name": "stdout",
          "text": "\b\b\b\b\b\b\b\b\b\b\b\b\b\b\b\b\b\b\b\b\b\b\b\b\b\b\b\b\b\b\b\b\b\b\b\b\b\b\b\b\b\b\b\b\b\b\b\b\b\b\b\b\b\b\b\b\b\b\b\b\b\b\b\b\b\b\b\b\b\b\b\b\b\b\r\u001b[1m26/34\u001b[0m \u001b[32mв”Ѓв”Ѓв”Ѓв”Ѓв”Ѓв”Ѓв”Ѓв”Ѓв”Ѓв”Ѓв”Ѓв”Ѓв”Ѓв”Ѓв”Ѓ\u001b[0m\u001b[37mв”Ѓв”Ѓв”Ѓв”Ѓв”Ѓ\u001b[0m \u001b[1m1s\u001b[0m 180ms/step - accuracy: 0.7121 - loss: 1.4050"
        },
        {
          "type": "stream",
          "name": "stdout",
          "text": "\b\b\b\b\b\b\b\b\b\b\b\b\b\b\b\b\b\b\b\b\b\b\b\b\b\b\b\b\b\b\b\b\b\b\b\b\b\b\b\b\b\b\b\b\b\b\b\b\b\b\b\b\b\b\b\b\b\b\b\b\b\b\b\b\b\b\b\b\b\b\b\b\b\b\r\u001b[1m27/34\u001b[0m \u001b[32mв”Ѓв”Ѓв”Ѓв”Ѓв”Ѓв”Ѓв”Ѓв”Ѓв”Ѓв”Ѓв”Ѓв”Ѓв”Ѓв”Ѓв”Ѓ\u001b[0m\u001b[37mв”Ѓв”Ѓв”Ѓв”Ѓв”Ѓ\u001b[0m \u001b[1m1s\u001b[0m 178ms/step - accuracy: 0.7121 - loss: 1.4058"
        },
        {
          "type": "stream",
          "name": "stdout",
          "text": "\b\b\b\b\b\b\b\b\b\b\b\b\b\b\b\b\b\b\b\b\b\b\b\b\b\b\b\b\b\b\b\b\b\b\b\b\b\b\b\b\b\b\b\b\b\b\b\b\b\b\b\b\b\b\b\b\b\b\b\b\b\b\b\b\b\b\b\b\b\b\b\b\b\b\r\u001b[1m28/34\u001b[0m \u001b[32mв”Ѓв”Ѓв”Ѓв”Ѓв”Ѓв”Ѓв”Ѓв”Ѓв”Ѓв”Ѓв”Ѓв”Ѓв”Ѓв”Ѓв”Ѓв”Ѓ\u001b[0m\u001b[37mв”Ѓв”Ѓв”Ѓв”Ѓ\u001b[0m \u001b[1m1s\u001b[0m 175ms/step - accuracy: 0.7120 - loss: 1.4065"
        },
        {
          "type": "stream",
          "name": "stdout",
          "text": "\b\b\b\b\b\b\b\b\b\b\b\b\b\b\b\b\b\b\b\b\b\b\b\b\b\b\b\b\b\b\b\b\b\b\b\b\b\b\b\b\b\b\b\b\b\b\b\b\b\b\b\b\b\b\b\b\b\b\b\b\b\b\b\b\b\b\b\b\b\b\b\b\b\b\r\u001b[1m29/34\u001b[0m \u001b[32mв”Ѓв”Ѓв”Ѓв”Ѓв”Ѓв”Ѓв”Ѓв”Ѓв”Ѓв”Ѓв”Ѓв”Ѓв”Ѓв”Ѓв”Ѓв”Ѓв”Ѓ\u001b[0m\u001b[37mв”Ѓв”Ѓв”Ѓ\u001b[0m \u001b[1m0s\u001b[0m 172ms/step - accuracy: 0.7120 - loss: 1.4070"
        },
        {
          "type": "stream",
          "name": "stdout",
          "text": "\b\b\b\b\b\b\b\b\b\b\b\b\b\b\b\b\b\b\b\b\b\b\b\b\b\b\b\b\b\b\b\b\b\b\b\b\b\b\b\b\b\b\b\b\b\b\b\b\b\b\b\b\b\b\b\b\b\b\b\b\b\b\b\b\b\b\b\b\b\b\b\b\b\b\r\u001b[1m30/34\u001b[0m \u001b[32mв”Ѓв”Ѓв”Ѓв”Ѓв”Ѓв”Ѓв”Ѓв”Ѓв”Ѓв”Ѓв”Ѓв”Ѓв”Ѓв”Ѓв”Ѓв”Ѓв”Ѓ\u001b[0m\u001b[37mв”Ѓв”Ѓв”Ѓ\u001b[0m \u001b[1m0s\u001b[0m 170ms/step - accuracy: 0.7120 - loss: 1.4075"
        },
        {
          "type": "stream",
          "name": "stdout",
          "text": "\b\b\b\b\b\b\b\b\b\b\b\b\b\b\b\b\b\b\b\b\b\b\b\b\b\b\b\b\b\b\b\b\b\b\b\b\b\b\b\b\b\b\b\b\b\b\b\b\b\b\b\b\b\b\b\b\b\b\b\b\b\b\b\b\b\b\b\b\b\b\b\b\b\b\r\u001b[1m31/34\u001b[0m \u001b[32mв”Ѓв”Ѓв”Ѓв”Ѓв”Ѓв”Ѓв”Ѓв”Ѓв”Ѓв”Ѓв”Ѓв”Ѓв”Ѓв”Ѓв”Ѓв”Ѓв”Ѓв”Ѓ\u001b[0m\u001b[37mв”Ѓв”Ѓ\u001b[0m \u001b[1m0s\u001b[0m 168ms/step - accuracy: 0.7120 - loss: 1.4082"
        },
        {
          "type": "stream",
          "name": "stdout",
          "text": "\b\b\b\b\b\b\b\b\b\b\b\b\b\b\b\b\b\b\b\b\b\b\b\b\b\b\b\b\b\b\b\b\b\b\b\b\b\b\b\b\b\b\b\b\b\b\b\b\b\b\b\b\b\b\b\b\b\b\b\b\b\b\b\b\b\b\b\b\b\b\b\b\b\b\r\u001b[1m32/34\u001b[0m \u001b[32mв”Ѓв”Ѓв”Ѓв”Ѓв”Ѓв”Ѓв”Ѓв”Ѓв”Ѓв”Ѓв”Ѓв”Ѓв”Ѓв”Ѓв”Ѓв”Ѓв”Ѓв”Ѓ\u001b[0m\u001b[37mв”Ѓв”Ѓ\u001b[0m \u001b[1m0s\u001b[0m 166ms/step - accuracy: 0.7119 - loss: 1.4093"
        },
        {
          "type": "stream",
          "name": "stdout",
          "text": "\b\b\b\b\b\b\b\b\b\b\b\b\b\b\b\b\b\b\b\b\b\b\b\b\b\b\b\b\b\b\b\b\b\b\b\b\b\b\b\b\b\b\b\b\b\b\b\b\b\b\b\b\b\b\b\b\b\b\b\b\b\b\b\b\b\b\b\b\b\b\b\b\b\b\r\u001b[1m33/34\u001b[0m \u001b[32mв”Ѓв”Ѓв”Ѓв”Ѓв”Ѓв”Ѓв”Ѓв”Ѓв”Ѓв”Ѓв”Ѓв”Ѓв”Ѓв”Ѓв”Ѓв”Ѓв”Ѓв”Ѓв”Ѓ\u001b[0m\u001b[37mв”Ѓ\u001b[0m \u001b[1m0s\u001b[0m 164ms/step - accuracy: 0.7117 - loss: 1.4103"
        },
        {
          "type": "stream",
          "name": "stdout",
          "text": "\b\b\b\b\b\b\b\b\b\b\b\b\b\b\b\b\b\b\b\b\b\b\b\b\b\b\b\b\b\b\b\b\b\b\b\b\b\b\b\b\b\b\b\b\b\b\b\b\b\b\b\b\b\b\b\b\b\b\b\b\b\b\b\b\b\b\b\b\b\b\b\b\b\b\r\u001b[1m34/34\u001b[0m \u001b[32mв”Ѓв”Ѓв”Ѓв”Ѓв”Ѓв”Ѓв”Ѓв”Ѓв”Ѓв”Ѓв”Ѓв”Ѓв”Ѓв”Ѓв”Ѓв”Ѓв”Ѓв”Ѓв”Ѓв”Ѓ\u001b[0m\u001b[37m\u001b[0m \u001b[1m0s\u001b[0m 162ms/step - accuracy: 0.7117 - loss: 1.4110"
        },
        {
          "type": "stream",
          "name": "stdout",
          "text": "\b\b\b\b\b\b\b\b\b\b\b\b\b\b\b\b\b\b\b\b\b\b\b\b\b\b\b\b\b\b\b\b\b\b\b\b\b\b\b\b\b\b\b\b\b\b\b\b\b\b\b\b\b\b\b\b\b\b\b\b\b\b\b\b\b\b\b\b\b\b\b\b\b\b\r\u001b[1m34/34\u001b[0m \u001b[32mв”Ѓв”Ѓв”Ѓв”Ѓв”Ѓв”Ѓв”Ѓв”Ѓв”Ѓв”Ѓв”Ѓв”Ѓв”Ѓв”Ѓв”Ѓв”Ѓв”Ѓв”Ѓв”Ѓв”Ѓ\u001b[0m\u001b[37m\u001b[0m \u001b[1m9s\u001b[0m 279ms/step - accuracy: 0.7091 - loss: 1.4366 - val_accuracy: 0.7281 - val_loss: 1.4333\n"
        },
        {
          "type": "execute_result",
          "text": "<keras.src.callbacks.history.History at 0x717c2b7cfb60>"
        }
      ]
    },
    "fcn-prediction-1": {
      "code_fingerprint": "sha256:9fc54a87cf9f4b9eae7d192077e9d575be07136d8318247cbb0794d189b26490",
      "kind": "text",
      "outputs": []
    },
    "fcn-prediction-2": {
      "code_fingerprint": "sha256:a3f3f45b81ad9be2800635adf96bfb28f2b6980b28630cd6f655b8c0bb3e2816",
      "kind": "text",
      "outputs": []
    },
    "fcn-prediction-3": {
      "code_fingerprint": "sha256:95c6d63a9df549d0c9b9df539414e847e26b171fdb0fc0e16c9038729799cca2",
      "kind": "asset",
      "outputs": [
        {
          "type": "display_data",
          "mime": "image/svg+xml",
          "asset": "fcn/fcn-prediction-3-1.svg",
          "bytes": 149137,
          "sha256": "sha256:4d3775bd1c876eb2e5cb8441e0d6423abe9ed4e48f655f0cf41182f9513ab937"
        }
      ]
    }
  }
}
